{"name": "rasdi", "country": []}
{"name": "rasekhi", "country": []}
{"name": "rasel", "country": [{"country_id": "BD", "probability": 0.9987833772785146}, {"country_id": "IT", "probability": 0.001216622721485293}]}
{"name": "rasha", "country": [{"country_id": "JO", "probability": 0.19283046260847964}, {"country_id": "SY", "probability": 0.16859680357762097}, {"country_id": "EG", "probability": 0.16331855061620967}]}
{"name": "rashad", "country": [{"country_id": "AZ", "probability": 0.8267454658713825}, {"country_id": "LB", "probability": 0.07092027383180416}, {"country_id": "IL", "probability": 0.03655406408892268}]}
{"name": "rashawn", "country": []}
{"name": "rashbinder", "country": []}
{"name": "rashed", "country": [{"country_id": "BD", "probability": 0.27472955813798017}, {"country_id": "AE", "probability": 0.24836067619760854}, {"country_id": "BH", "probability": 0.11943711992016766}]}
{"name": "rasheda", "country": []}
{"name": "rashedur", "country": []}
{"name": "rasheed", "country": [{"country_id": "NG", "probability": 0.3397755883686609}, {"country_id": "PK", "probability": 0.25836572411757996}, {"country_id": "JO", "probability": 0.15459692756811486}]}
{"name": "rashelle", "country": []}
{"name": "rashemi", "country": []}
{"name": "rashesh", "country": []}
{"name": "rashi", "country": [{"country_id": "IN", "probability": 1}]}
{"name": "rashid", "country": [{"country_id": "PK", "probability": 0.15849517526669296}, {"country_id": "OM", "probability": 0.14332542483344704}, {"country_id": "AE", "probability": 0.13938211215975954}]}
{"name": "rashidah", "country": [{"country_id": "MY", "probability": 1}]}
{"name": "rashin", "country": [{"country_id": "IR", "probability": 1}]}
{"name": "raship", "country": []}
{"name": "rashmi", "country": [{"country_id": "IN", "probability": 0.9884029344124364}, {"country_id": "GB", "probability": 0.011597065587563585}]}
{"name": "rashotte", "country": []}
{"name": "rashpal", "country": []}
{"name": "rasif", "country": []}
{"name": "rasik", "country": [{"country_id": "IN", "probability": 1}]}
{"name": "rasika", "country": [{"country_id": "LK", "probability": 0.9789242681487077}, {"country_id": "IN", "probability": 0.021075731851292176}]}
{"name": "rasim", "country": [{"country_id": "AZ", "probability": 0.6753297312719284}, {"country_id": "BA", "probability": 0.10814973286108018}, {"country_id": "TR", "probability": 0.08401834651119199}]}
{"name": "rasimah", "country": []}
{"name": "rasit", "country": [{"country_id": "TR", "probability": 0.8044211862171952}, {"country_id": "DE", "probability": 0.19557881378280503}]}
{"name": "rasmi", "country": []}
{"name": "rasmiah", "country": []}
{"name": "rasmieh", "country": []}
{"name": "rasmieyh", "country": []}
{"name": "rasmus", "country": [{"country_id": "DK", "probability": 0.642572377042454}, {"country_id": "SE", "probability": 0.16651583232611883}, {"country_id": "EE", "probability": 0.08030433558881732}]}
{"name": "rasmussen", "country": []}
{"name": "rasool", "country": [{"country_id": "IR", "probability": 1.0000000000000002}]}
{"name": "rasoul", "country": [{"country_id": "IR", "probability": 1}]}
{"name": "rasouli", "country": []}
{"name": "rassoul", "country": [{"country_id": "SN", "probability": 1}]}
{"name": "rastan", "country": []}
{"name": "rastegarpanah", "country": []}
{"name": "rastislav", "country": [{"country_id": "SK", "probability": 0.9663708133656023}, {"country_id": "CZ", "probability": 0.027406203797874902}, {"country_id": "GB", "probability": 0.006222982836522851}]}
{"name": "rastislava", "country": []}
{"name": "rastko", "country": [{"country_id": "RS", "probability": 1}]}
{"name": "rasu", "country": []}
{"name": "rasul", "country": [{"country_id": "AZ", "probability": 0.6059267662655289}, {"country_id": "KZ", "probability": 0.3340026474583184}, {"country_id": "RU", "probability": 0.05572286843787023}]}
{"name": "rasula", "country": []}
{"name": "rasumus", "country": []}
{"name": "rasyid", "country": [{"country_id": "ID", "probability": 1}]}
{"name": "rat", "country": [{"country_id": "TH", "probability": 0.7431271117487843}, {"country_id": "RO", "probability": 0.1873028381778451}, {"country_id": "GB", "probability": 0.03308396919910779}]}
{"name": "ratan", "country": [{"country_id": "IN", "probability": 1}]}
{"name": "ratana", "country": [{"country_id": "TH", "probability": 1}]}
{"name": "ratchadaporn", "country": [{"country_id": "TH", "probability": 1}]}
{"name": "rath", "country": [{"country_id": "TH", "probability": 1}]}
{"name": "ratha", "country": [{"country_id": "MY", "probability": 0.6628532987338912}, {"country_id": "TH", "probability": 0.33714670126610885}]}
{"name": "rathachai", "country": []}
{"name": "rathava", "country": []}
{"name": "rathe", "country": []}
{"name": "rathiah", "country": []}
{"name": "rathimala", "country": []}
{"name": "rathinasamy", "country": []}
{"name": "rathineswaran", "country": []}
{"name": "rathna", "country": [{"country_id": "IN", "probability": 1}]}
{"name": "rathod", "country": []}
{"name": "rati", "country": [{"country_id": "GE", "probability": 0.9640792059339179}, {"country_id": "IN", "probability": 0.03592079406608215}]}
{"name": "ratih", "country": [{"country_id": "ID", "probability": 1}]}
{"name": "ratinho", "country": [{"country_id": "PT", "probability": 1.0000000000000002}]}
{"name": "ratko", "country": [{"country_id": "ME", "probability": 0.4796256791787526}, {"country_id": "RS", "probability": 0.19893352331090786}, {"country_id": "BA", "probability": 0.175683166557205}]}
{"name": "ratna", "country": [{"country_id": "ID", "probability": 0.8814108629016895}, {"country_id": "MY", "probability": 0.054271278931978056}, {"country_id": "IN", "probability": 0.050743387350176736}]}
{"name": "ratnadeep", "country": []}
{"name": "ratnakirti", "country": []}
{"name": "ratnaraj", "country": []}
{"name": "ratnasingham", "country": []}
{"name": "ratnesh", "country": [{"country_id": "IN", "probability": 1}]}
{"name": "rattakorn", "country": []}
{"name": "rattan", "country": [{"country_id": "IN", "probability": 1}]}
{"name": "rattana", "country": [{"country_id": "TH", "probability": 1}]}
{"name": "rattanaritnont", "country": []}
{"name": "rattikorn", "country": []}
{"name": "ratul", "country": [{"country_id": "IN", "probability": 1}]}
{"name": "raudel", "country": []}
{"name": "raudhah", "country": []}
{"name": "raudlatul", "country": []}
{"name": "rauf", "country": [{"country_id": "AZ", "probability": 0.8757829905129492}, {"country_id": "PK", "probability": 0.07220018893241315}, {"country_id": "GH", "probability": 0.02116075469759817}]}
{"name": "raul", "country": [{"country_id": "ES", "probability": 0.08164558026217401}, {"country_id": "PE", "probability": 0.07523694866817272}, {"country_id": "SV", "probability": 0.0683611672971267}]}
{"name": "raula", "country": []}
{"name": "raunak", "country": [{"country_id": "IN", "probability": 1}]}
{"name": "raunaq", "country": []}
{"name": "rauno", "country": [{"country_id": "EE", "probability": 0.7422425318626589}, {"country_id": "FI", "probability": 0.25775746813734113}]}
{"name": "raushan", "country": [{"country_id": "KZ", "probability": 0.9523645312718645}, {"country_id": "IN", "probability": 0.04763546872813549}]}
{"name": "rautava", "country": []}
{"name": "raux", "country": [{"country_id": "FR", "probability": 1}]}
{"name": "raval", "country": []}
{"name": "raveewan", "country": []}
{"name": "raven", "country": [{"country_id": "GH", "probability": 0.1587002229445713}, {"country_id": "ZA", "probability": 0.1480812940365361}, {"country_id": "CI", "probability": 0.09448593275825411}]}
{"name": "ravenna", "country": []}
{"name": "ravi", "country": [{"country_id": "IN", "probability": 0.3955775076251657}, {"country_id": "LK", "probability": 0.18939135443531854}, {"country_id": "NP", "probability": 0.15327304214640386}]}
{"name": "ravichandra", "country": [{"country_id": "IN", "probability": 1}]}
{"name": "ravie", "country": []}
{"name": "ravikant", "country": [{"country_id": "IN", "probability": 1}]}
{"name": "ravikarn", "country": []}
{"name": "ravikiran", "country": [{"country_id": "IN", "probability": 1}]}
{"name": "ravikumar", "country": [{"country_id": "IN", "probability": 1}]}
{"name": "ravil", "country": [{"country_id": "AZ", "probability": 0.7855783241210303}, {"country_id": "RU", "probability": 0.21442167587896946}]}
{"name": "ravin", "country": [{"country_id": "MU", "probability": 0.8546728601464121}, {"country_id": "MY", "probability": 0.07691766629602992}, {"country_id": "IN", "probability": 0.06840947355755791}]}
{"name": "ravina", "country": []}
{"name": "ravinder", "country": [{"country_id": "IN", "probability": 0.9663105994966246}, {"country_id": "GB", "probability": 0.03368940050337531}]}
{"name": "ravinderpal", "country": []}
{"name": "ravindra", "country": [{"country_id": "LK", "probability": 0.6009060176070733}, {"country_id": "IN", "probability": 0.39909398239292676}]}
{"name": "ravindranath", "country": []}
{"name": "ravinesan", "country": []}
{"name": "ravinesh", "country": []}
{"name": "ravinsingh", "country": []}
{"name": "raviraj", "country": [{"country_id": "IN", "probability": 1}]}
{"name": "ravisankar", "country": []}
{"name": "ravish", "country": [{"country_id": "IN", "probability": 1}]}
{"name": "ravisha", "country": []}
{"name": "ravishankar", "country": [{"country_id": "IN", "probability": 1}]}
{"name": "ravishanker", "country": []}
{"name": "ravit", "country": [{"country_id": "IL", "probability": 1}]}
{"name": "ravita", "country": []}
{"name": "raviv", "country": []}
{"name": "ravjeer", "country": []}
{"name": "ravneet", "country": [{"country_id": "IN", "probability": 1}]}
{"name": "ravula", "country": []}
{"name": "ravy", "country": []}
{"name": "rawad", "country": [{"country_id": "LB", "probability": 0.8409930100266451}, {"country_id": "AE", "probability": 0.11568306133340894}, {"country_id": "SA", "probability": 0.04332392863994605}]}
{"name": "rawan", "country": [{"country_id": "JO", "probability": 0.3876215010193061}, {"country_id": "IL", "probability": 0.16167255862627594}, {"country_id": "KW", "probability": 0.11247372971385847}]}
{"name": "rawee", "country": [{"country_id": "TH", "probability": 1}]}
{"name": "rawley", "country": []}
{"name": "rawn", "country": []}
{"name": "rawya", "country": [{"country_id": "MA", "probability": 0.5171108855401577}, {"country_id": "TN", "probability": 0.4828891144598422}]}
{"name": "ray", "country": [{"country_id": "HK", "probability": 0.1252685489217675}, {"country_id": "MT", "probability": 0.09640452595606586}, {"country_id": "TW", "probability": 0.07283764542329739}]}
{"name": "raya", "country": [{"country_id": "IL", "probability": 0.32456144292996897}, {"country_id": "JO", "probability": 0.3186616275496219}, {"country_id": "LB", "probability": 0.1145475897309987}]}
{"name": "rayadurgam", "country": []}
{"name": "rayala", "country": []}
{"name": "raychel", "country": []}
{"name": "rayda", "country": []}
{"name": "raydonal", "country": []}
{"name": "rayed", "country": [{"country_id": "SA", "probability": 1}]}
{"name": "rayelle", "country": []}
{"name": "rayette", "country": []}
{"name": "rayford", "country": []}
{"name": "rayguang", "country": []}
{"name": "rayhan", "country": [{"country_id": "BD", "probability": 0.9295610177576554}, {"country_id": "ID", "probability": 0.04881822358865312}, {"country_id": "GB", "probability": 0.01681349906267339}]}
{"name": "rayi", "country": [{"country_id": "ID", "probability": 1}]}
{"name": "rayid", "country": []}
{"name": "rayka", "country": []}
{"name": "raylene", "country": []}
{"name": "raymay", "country": []}
{"name": "raymie", "country": []}
{"name": "raymond", "country": [{"country_id": "MT", "probability": 0.08019679173142101}, {"country_id": "HK", "probability": 0.06115668812537877}, {"country_id": "US", "probability": 0.050119505973913306}]}
{"name": "raymondalain", "country": []}
{"name": "raymonde", "country": [{"country_id": "CI", "probability": 0.32761268376506664}, {"country_id": "FR", "probability": 0.20142296357208608}, {"country_id": "CM", "probability": 0.19470103102896907}]}
{"name": "raymund", "country": [{"country_id": "PH", "probability": 0.991433929962298}, {"country_id": "DE", "probability": 0.008566070037702076}]}
{"name": "raymundo", "country": [{"country_id": "MX", "probability": 0.718211195129591}, {"country_id": "PH", "probability": 0.24149236783205122}, {"country_id": "US", "probability": 0.0349758913220755}]}
{"name": "rayna", "country": [{"country_id": "BG", "probability": 0.9938394970656668}, {"country_id": "FR", "probability": 0.006160502934333243}]}
{"name": "raynaud", "country": [{"country_id": "FR", "probability": 1}]}
{"name": "rayner", "country": [{"country_id": "MY", "probability": 1}]}
{"name": "rayol", "country": []}
{"name": "rayyan", "country": [{"country_id": "SA", "probability": 0.7123758132492146}, {"country_id": "MY", "probability": 0.23876347697991884}, {"country_id": "GB", "probability": 0.04886070977086646}]}
{"name": "rayyaung", "country": []}
{"name": "raz", "country": [{"country_id": "IL", "probability": 0.6803409202978584}, {"country_id": "GB", "probability": 0.15284588483248857}, {"country_id": "RO", "probability": 0.07222592738800374}]}
{"name": "raza", "country": [{"country_id": "PK", "probability": 0.8181031377617292}, {"country_id": "AE", "probability": 0.09836960239649067}, {"country_id": "IN", "probability": 0.028388361960884505}]}
{"name": "razali", "country": [{"country_id": "MY", "probability": 0.7133998166351618}, {"country_id": "SG", "probability": 0.28660018336483806}]}
{"name": "razan", "country": [{"country_id": "JO", "probability": 0.5415032775464327}, {"country_id": "IL", "probability": 0.15434273081022776}, {"country_id": "SA", "probability": 0.13273038524387715}]}
{"name": "razana", "country": []}
{"name": "razavi", "country": []}
{"name": "razeghi", "country": []}
{"name": "razep", "country": []}
{"name": "razeyah", "country": []}
{"name": "razi", "country": [{"country_id": "PK", "probability": 0.3243233552769464}, {"country_id": "IL", "probability": 0.20343786964906915}, {"country_id": "TN", "probability": 0.15282814728056862}]}
{"name": "razib", "country": [{"country_id": "BD", "probability": 1}]}
{"name": "razieh", "country": [{"country_id": "IR", "probability": 1}]}
{"name": "raziel", "country": [{"country_id": "PH", "probability": 0.6101360841287454}, {"country_id": "IT", "probability": 0.20602688448781134}, {"country_id": "FR", "probability": 0.10977656175408372}]}
{"name": "raziyeh", "country": []}
{"name": "razmig", "country": []}
{"name": "razmik", "country": [{"country_id": "AM", "probability": 1}]}
{"name": "razvan", "country": [{"country_id": "RO", "probability": 0.9236656367386838}, {"country_id": "", "probability": 0.040681980535269634}, {"country_id": "IT", "probability": 0.008211014498328091}]}
{"name": "razvanandrei", "country": []}
{"name": "razvangeorge", "country": []}
{"name": "rdddhi", "country": []}
{"name": "rdioud", "country": []}
{"name": "rdouan", "country": []}
{"name": "rdw", "country": []}
{"name": "re", "country": [{"country_id": "IT", "probability": 0.2186515749330912}, {"country_id": "KR", "probability": 0.1949106088687986}, {"country_id": "ID", "probability": 0.13886171760750327}]}
{"name": "rea", "country": [{"country_id": "PH", "probability": 0.33465999022875886}, {"country_id": "HR", "probability": 0.17774428178420437}, {"country_id": "AL", "probability": 0.13462685500956936}]}
{"name": "reachlaw", "country": []}
{"name": "read", "country": [{"country_id": "DZ", "probability": 0.7939808136046306}, {"country_id": "GB", "probability": 0.20601918639536962}]}
{"name": "reader", "country": []}
{"name": "ready", "country": []}
{"name": "real", "country": [{"country_id": "KW", "probability": 0.13891178501373244}, {"country_id": "SA", "probability": 0.08590090836507644}, {"country_id": "GH", "probability": 0.08473699335516956}]}
{"name": "rean", "country": [{"country_id": "PH", "probability": 1}]}
{"name": "reaz", "country": [{"country_id": "BD", "probability": 0.7123818569498213}, {"country_id": "MU", "probability": 0.28761814305017874}]}
{"name": "rebbeca", "country": []}
{"name": "rebeca", "country": [{"country_id": "CR", "probability": 0.2654689159300318}, {"country_id": "ES", "probability": 0.19347188808171314}, {"country_id": "VE", "probability": 0.09373078352616818}]}
{"name": "rebecca", "country": [{"country_id": "VE", "probability": 0.06886744269093896}, {"country_id": "MX", "probability": 0.05852277646416075}, {"country_id": "AU", "probability": 0.038814759385817056}]}
{"name": "rebeccah", "country": []}
{"name": "rebecka", "country": [{"country_id": "SE", "probability": 0.9830004548879243}, {"country_id": "DE", "probability": 0.01699954511207554}]}
{"name": "rebeka", "country": [{"country_id": "SI", "probability": 0.3538941673139476}, {"country_id": "HU", "probability": 0.28701695046269665}, {"country_id": "SK", "probability": 0.10921262118467286}]}
{"name": "rebekah", "country": [{"country_id": "GB", "probability": 0.5620826480684138}, {"country_id": "US", "probability": 0.3214578232985398}, {"country_id": "PH", "probability": 0.11645952863304643}]}
{"name": "rebekka", "country": [{"country_id": "DE", "probability": 0.20306905483105406}, {"country_id": "DK", "probability": 0.20275188116867873}, {"country_id": "NO", "probability": 0.1767957245988191}]}
{"name": "rebekkah", "country": []}
{"name": "rebild", "country": []}
{"name": "rebiun", "country": []}
{"name": "rebwar", "country": [{"country_id": "IQ", "probability": 0.9874255313005078}, {"country_id": "GB", "probability": 0.012574468699492152}]}
{"name": "received", "country": []}
{"name": "recep", "country": [{"country_id": "TR", "probability": 0.7430777543577881}, {"country_id": "", "probability": 0.10214055181921643}, {"country_id": "AZ", "probability": 0.04823490635485363}]}
{"name": "recerca", "country": []}
{"name": "recio", "country": [{"country_id": "ES", "probability": 1}]}
{"name": "reda", "country": [{"country_id": "DZ", "probability": 0.2164721786657355}, {"country_id": "MA", "probability": 0.2055392026628784}, {"country_id": "LT", "probability": 0.1452281201788238}]}
{"name": "redaccion", "country": []}
{"name": "redaktion", "country": []}
{"name": "reddi", "country": []}
{"name": "reddy", "country": [{"country_id": "CD", "probability": 0.5649388129431913}, {"country_id": "IN", "probability": 0.3305935818845609}, {"country_id": "ID", "probability": 0.09487834615764014}]}
{"name": "redecker", "country": []}
{"name": "redelmacias", "country": []}
{"name": "redhead", "country": []}
{"name": "redhouane", "country": [{"country_id": "DZ", "probability": 1}]}
{"name": "rediet", "country": [{"country_id": "ET", "probability": 1.0000000000000002}]}
{"name": "redmann", "country": []}
{"name": "redmond", "country": []}
{"name": "redouan", "country": [{"country_id": "MA", "probability": 0.566428137885184}, {"country_id": "NL", "probability": 0.19762399880160864}, {"country_id": "BE", "probability": 0.09732388855870963}]}
{"name": "redwaan", "country": []}
{"name": "ree", "country": [{"country_id": "TH", "probability": 0.31188527226383905}, {"country_id": "ZA", "probability": 0.2705553808433646}, {"country_id": "SA", "probability": 0.2204496478465549}]}
{"name": "reece", "country": [{"country_id": "AU", "probability": 0.4945635490604791}, {"country_id": "GB", "probability": 0.4059083279165806}, {"country_id": "ZA", "probability": 0.06971670748341473}]}
{"name": "reed", "country": [{"country_id": "US", "probability": 0.9037760685340896}, {"country_id": "GB", "probability": 0.06883894306143767}, {"country_id": "FR", "probability": 0.027384988404472697}]}
{"name": "reeflauren", "country": []}
{"name": "reelika", "country": [{"country_id": "EE", "probability": 1}]}
{"name": "reem", "country": [{"country_id": "BH", "probability": 0.10710158796453355}, {"country_id": "YE", "probability": 0.09889179190964612}, {"country_id": "SA", "probability": 0.0984220000668751}]}
{"name": "reema", "country": [{"country_id": "SA", "probability": 0.2703869623349063}, {"country_id": "JO", "probability": 0.2336024961865644}, {"country_id": "BH", "probability": 0.21078427144706122}]}
{"name": "reember", "country": []}
{"name": "reena", "country": [{"country_id": "MU", "probability": 0.6038544031285404}, {"country_id": "IN", "probability": 0.16246377514015656}, {"country_id": "SG", "probability": 0.07344191022320837}]}
{"name": "reese", "country": [{"country_id": "US", "probability": 0.7252568087741094}, {"country_id": "GB", "probability": 0.2306501574615343}, {"country_id": "FR", "probability": 0.0440930337643564}]}
{"name": "reeshad", "country": []}
{"name": "reeta", "country": [{"country_id": "FI", "probability": 0.8580309504477708}, {"country_id": "IN", "probability": 0.1419690495522291}]}
{"name": "reeti", "country": []}
{"name": "reetta", "country": [{"country_id": "FI", "probability": 1}]}
{"name": "reeva", "country": []}
{"name": "reeve", "country": []}
{"name": "refael", "country": []}
{"name": "refik", "country": [{"country_id": "BA", "probability": 0.4178544899343351}, {"country_id": "TR", "probability": 0.37749865561491935}, {"country_id": "RS", "probability": 0.1148329816403537}]}
{"name": "refk", "country": []}
{"name": "reg", "country": [{"country_id": "CA", "probability": 0.39070890816437703}, {"country_id": "GB", "probability": 0.1966605307156285}, {"country_id": "ZA", "probability": 0.16364380414216903}]}
{"name": "regan", "country": [{"country_id": "ZA", "probability": 0.49517919068287664}, {"country_id": "US", "probability": 0.21506044154784396}, {"country_id": "PH", "probability": 0.15521067111423908}]}
{"name": "regardt", "country": []}
{"name": "reggie", "country": [{"country_id": "PH", "probability": 0.3290116878841081}, {"country_id": "GH", "probability": 0.174805732022955}, {"country_id": "ZA", "probability": 0.16643791159460705}]}
{"name": "regi", "country": [{"country_id": "HU", "probability": 0.2827101514104407}, {"country_id": "CH", "probability": 0.18709368603983936}, {"country_id": "ID", "probability": 0.12855783373700633}]}
{"name": "regiane", "country": [{"country_id": "BR", "probability": 0.7047166387226944}, {"country_id": "JP", "probability": 0.21644832559437044}, {"country_id": "PT", "probability": 0.06936975376198781}]}
{"name": "regien", "country": []}
{"name": "regin", "country": [{"country_id": "PH", "probability": 1}]}
{"name": "regina", "country": [{"country_id": "LT", "probability": 0.2060881884674842}, {"country_id": "EE", "probability": 0.06259818632042685}, {"country_id": "GH", "probability": 0.05445683694397978}]}
{"name": "reginald", "country": [{"country_id": "GH", "probability": 0.2891155879424184}, {"country_id": "US", "probability": 0.15960173016848414}, {"country_id": "PH", "probability": 0.15053632228155586}]}
{"name": "reginaldo", "country": [{"country_id": "GQ", "probability": 0.5475448404369092}, {"country_id": "BR", "probability": 0.18978806120357805}, {"country_id": "MZ", "probability": 0.14850095795183968}]}
{"name": "regine", "country": [{"country_id": "CM", "probability": 0.36197126191347595}, {"country_id": "PH", "probability": 0.30257624652495657}, {"country_id": "FR", "probability": 0.09504337190654549}]}
{"name": "regino", "country": [{"country_id": "PH", "probability": 0.8829526309295006}, {"country_id": "ES", "probability": 0.11704736907049934}]}
{"name": "regis", "country": [{"country_id": "CG", "probability": 0.27627297744017143}, {"country_id": "GA", "probability": 0.1945735241029455}, {"country_id": "ZW", "probability": 0.1421238446430223}]}
{"name": "regit", "country": []}
{"name": "regita", "country": []}
{"name": "regna", "country": [{"country_id": "CZ", "probability": 1}]}
{"name": "reha", "country": [{"country_id": "TR", "probability": 1}]}
{"name": "rehab", "country": [{"country_id": "EG", "probability": 0.4803143072438064}, {"country_id": "SD", "probability": 0.43429633207197726}, {"country_id": "SA", "probability": 0.06872064803235552}]}
{"name": "reham", "country": [{"country_id": "EG", "probability": 0.5178652193680459}, {"country_id": "JO", "probability": 0.1765903991048146}, {"country_id": "IL", "probability": 0.14646196683202686}]}
{"name": "rehama", "country": []}
{"name": "rehan", "country": [{"country_id": "PK", "probability": 0.7795872957022583}, {"country_id": "IN", "probability": 0.09975622362551828}, {"country_id": "AE", "probability": 0.063443164129199}]}
{"name": "rehana", "country": [{"country_id": "PK", "probability": 0.6746501707010957}, {"country_id": "ZA", "probability": 0.24888743567968524}, {"country_id": "GB", "probability": 0.07646239361921921}]}
{"name": "rehema", "country": [{"country_id": "TZ", "probability": 0.9109498386400448}, {"country_id": "KE", "probability": 0.08905016135995533}]}
{"name": "rehnuma", "country": []}
{"name": "rei", "country": [{"country_id": "JP", "probability": 0.4612790056707595}, {"country_id": "AL", "probability": 0.38694910532382154}, {"country_id": "PH", "probability": 0.04024475673508422}]}
{"name": "reichl", "country": []}
{"name": "reid", "country": [{"country_id": "CA", "probability": 0.5911487931136294}, {"country_id": "US", "probability": 0.4088512068863706}]}
{"name": "reidar", "country": [{"country_id": "NO", "probability": 0.9353195438972617}, {"country_id": "SE", "probability": 0.06468045610273822}]}
{"name": "reidun", "country": [{"country_id": "NO", "probability": 1}]}
{"name": "reigo", "country": [{"country_id": "EE", "probability": 1}]}
{"name": "reihane", "country": []}
{"name": "reihaneh", "country": [{"country_id": "IR", "probability": 1}]}
{"name": "reihonna", "country": []}
{"name": "reija", "country": [{"country_id": "FI", "probability": 1}]}
{"name": "reijane", "country": []}
{"name": "reiji", "country": [{"country_id": "JP", "probability": 1}]}
{"name": "reijo", "country": [{"country_id": "FI", "probability": 0.9357940081411544}, {"country_id": "SE", "probability": 0.0642059918588455}]}
{"name": "reik", "country": [{"country_id": "DE", "probability": 1}]}
{"name": "reike", "country": []}
{"name": "reiko", "country": [{"country_id": "JP", "probability": 0.9833254971012846}, {"country_id": "DE", "probability": 0.016674502898715384}]}
{"name": "reiley", "country": []}
{"name": "reilly", "country": []}
{"name": "reima", "country": [{"country_id": "FI", "probability": 0.9999999999999999}]}
{"name": "reimara", "country": []}
{"name": "reimbay", "country": []}
{"name": "reimer", "country": []}
{"name": "rein", "country": [{"country_id": "EE", "probability": 0.7818331357060738}, {"country_id": "NL", "probability": 0.151734594743777}, {"country_id": "PH", "probability": 0.024738443516576128}]}
{"name": "reina", "country": [{"country_id": "JP", "probability": 0.273089026578443}, {"country_id": "VE", "probability": 0.23783553213236844}, {"country_id": "PH", "probability": 0.17835101422263566}]}
{"name": "reinaldo", "country": [{"country_id": "VE", "probability": 0.3071984726669737}, {"country_id": "BR", "probability": 0.22546981126331045}, {"country_id": "MZ", "probability": 0.12931587930857322}]}
{"name": "reinard", "country": []}
{"name": "reinart", "country": []}
{"name": "reinder", "country": [{"country_id": "NL", "probability": 1}]}
{"name": "reiner", "country": [{"country_id": "DE", "probability": 0.7196452545447741}, {"country_id": "PH", "probability": 0.10180716861880473}, {"country_id": "AT", "probability": 0.09219273338551418}]}
{"name": "reiners", "country": []}
{"name": "reingard", "country": []}
{"name": "reinhard", "country": [{"country_id": "AT", "probability": 0.7334127652533191}, {"country_id": "DE", "probability": 0.18242334289888532}, {"country_id": "ID", "probability": 0.029363521876951258}]}
{"name": "reinhardiris", "country": []}
{"name": "reinhardt", "country": [{"country_id": "ZA", "probability": 0.8358559321469553}, {"country_id": "DE", "probability": 0.16414406785304453}]}
{"name": "reinhart", "country": [{"country_id": "DE", "probability": 1}]}
{"name": "reinhartzberger", "country": []}
{"name": "reinhild", "country": [{"country_id": "DE", "probability": 1}]}
{"name": "reinhilde", "country": [{"country_id": "BE", "probability": 0.8468617678926368}, {"country_id": "DE", "probability": 0.15313823210736324}]}
{"name": "reinhold", "country": [{"country_id": "AT", "probability": 0.6360525445514582}, {"country_id": "DE", "probability": 0.3639474554485417}]}
{"name": "reini", "country": [{"country_id": "AT", "probability": 0.9516709123001037}, {"country_id": "DE", "probability": 0.04832908769989617}]}
{"name": "reinier", "country": [{"country_id": "CU", "probability": 0.8948664433942888}, {"country_id": "NL", "probability": 0.09172788648249851}, {"country_id": "PH", "probability": 0.012308895234359327}]}
{"name": "reinilson", "country": []}
{"name": "reinmar", "country": []}
{"name": "reinoso", "country": []}
{"name": "reinoud", "country": [{"country_id": "NL", "probability": 1}]}
{"name": "reinout", "country": [{"country_id": "NL", "probability": 0.6890546547486416}, {"country_id": "BE", "probability": 0.3109453452513584}]}
{"name": "reis", "country": [{"country_id": "AO", "probability": 0.3446838681709752}, {"country_id": "TR", "probability": 0.33070089904023847}, {"country_id": "PT", "probability": 0.19267837001438745}]}
{"name": "reisa", "country": []}
{"name": "reise", "country": []}
{"name": "reixia", "country": []}
{"name": "rejab", "country": []}
{"name": "rejane", "country": [{"country_id": "BR", "probability": 0.78280521698559}, {"country_id": "PT", "probability": 0.07678708224713857}, {"country_id": "FR", "probability": 0.06833085851326842}]}
{"name": "rejean", "country": [{"country_id": "CA", "probability": 0.8265353414814672}, {"country_id": "PH", "probability": 0.17346465851853282}]}
{"name": "rejeskiw", "country": []}
{"name": "reji", "country": [{"country_id": "IN", "probability": 1}]}
{"name": "rejikumar", "country": []}
{"name": "reka", "country": [{"country_id": "RO", "probability": 0.6354560271756988}, {"country_id": "", "probability": 0.16699032333305372}, {"country_id": "ID", "probability": 0.13545270002939336}]}
{"name": "rekha", "country": [{"country_id": "IN", "probability": 0.6333164596621343}, {"country_id": "SG", "probability": 0.24745180856733762}, {"country_id": "MY", "probability": 0.10420727031377361}]}
{"name": "rekhi", "country": []}
{"name": "rekin", "country": []}
{"name": "rela", "country": []}
{"name": "relacoes", "country": []}
{"name": "relano", "country": []}
{"name": "relda", "country": []}
{"name": "relebohile", "country": [{"country_id": "LS", "probability": 1}]}
{"name": "relisa", "country": []}
{"name": "relja", "country": [{"country_id": "RS", "probability": 1}]}
{"name": "rema", "country": [{"country_id": "IL", "probability": 0.2915320891246772}, {"country_id": "JO", "probability": 0.26545772275855894}, {"country_id": "SA", "probability": 0.22360415505507386}]}
{"name": "rematus", "country": []}
{"name": "rembrand", "country": []}
{"name": "remco", "country": [{"country_id": "NL", "probability": 0.9853991859576662}, {"country_id": "BE", "probability": 0.014600814042333779}]}
{"name": "remedios", "country": [{"country_id": "PH", "probability": 0.7125780651625937}, {"country_id": "ES", "probability": 0.274365498087133}, {"country_id": "IT", "probability": 0.01305643675027329}]}
{"name": "remesan", "country": []}
{"name": "remi", "country": [{"country_id": "NO", "probability": 0.15223267712402136}, {"country_id": "FR", "probability": 0.12672632580836285}, {"country_id": "TG", "probability": 0.0897922856990652}]}
{"name": "remia", "country": [{"country_id": "PH", "probability": 1}]}
{"name": "remigijus", "country": [{"country_id": "LT", "probability": 0.9940714992125268}, {"country_id": "GB", "probability": 0.005928500787473051}]}
{"name": "remigio", "country": [{"country_id": "PH", "probability": 0.6295619865735675}, {"country_id": "IT", "probability": 0.22578879659231468}, {"country_id": "ES", "probability": 0.1446492168341178}]}
{"name": "remigiusz", "country": [{"country_id": "PL", "probability": 0.8754703359792637}, {"country_id": "GB", "probability": 0.05583081267327579}, {"country_id": "", "probability": 0.055826296662820775}]}
{"name": "remko", "country": [{"country_id": "NL", "probability": 0.9999999999999999}]}
{"name": "remo", "country": [{"country_id": "CH", "probability": 0.5155256791727133}, {"country_id": "EG", "probability": 0.13878802299503687}, {"country_id": "SA", "probability": 0.10316908414934386}]}
{"name": "remom", "country": []}
{"name": "remus", "country": [{"country_id": "RO", "probability": 0.8780600089310937}, {"country_id": "", "probability": 0.03505692514110996}, {"country_id": "PH", "probability": 0.029146213593262856}]}
{"name": "remy", "country": [{"country_id": "CD", "probability": 0.21003289514011386}, {"country_id": "NL", "probability": 0.11540067078080321}, {"country_id": "LU", "probability": 0.08405363166225706}]}
{"name": "remya", "country": [{"country_id": "IN", "probability": 1}]}
{"name": "remzi", "country": [{"country_id": "TR", "probability": 0.41991937211653585}, {"country_id": "AL", "probability": 0.17933233096095866}, {"country_id": "AZ", "probability": 0.14350375854268455}]}
{"name": "ren", "country": [{"country_id": "DK", "probability": 0.129929435140398}, {"country_id": "CH", "probability": 0.0854370066018991}, {"country_id": "DE", "probability": 0.08452220958564738}]}
{"name": "rena", "country": [{"country_id": "AZ", "probability": 0.3903350805579989}, {"country_id": "GR", "probability": 0.2037923538532889}, {"country_id": "CZ", "probability": 0.06945020099406393}]}
{"name": "renaat", "country": [{"country_id": "BE", "probability": 1}]}
{"name": "renae", "country": [{"country_id": "US", "probability": 1}]}
{"name": "renai", "country": []}
{"name": "renaldo", "country": [{"country_id": "AL", "probability": 0.4316927335978136}, {"country_id": "ZA", "probability": 0.226430981915084}, {"country_id": "NL", "probability": 0.17030969411032504}]}
{"name": "renan", "country": [{"country_id": "BR", "probability": 0.7897787170020213}, {"country_id": "PH", "probability": 0.09541433345958338}, {"country_id": "JP", "probability": 0.0521370515220926}]}
{"name": "renana", "country": []}
{"name": "renanulrich", "country": []}
{"name": "renat", "country": [{"country_id": "AZ", "probability": 0.5105422016126545}, {"country_id": "KZ", "probability": 0.34141376189232053}, {"country_id": "RU", "probability": 0.13205960642650474}]}
{"name": "renata", "country": [{"country_id": "LT", "probability": 0.2238270284814057}, {"country_id": "CZ", "probability": 0.13951357902536463}, {"country_id": "PL", "probability": 0.10180578129544146}]}
{"name": "renatagraziela", "country": []}
{"name": "renate", "country": [{"country_id": "AT", "probability": 0.40321351274988715}, {"country_id": "NL", "probability": 0.1508891322988079}, {"country_id": "NO", "probability": 0.13863943224194966}]}
{"name": "renato", "country": [{"country_id": "BR", "probability": 0.24411840325140005}, {"country_id": "PT", "probability": 0.08542058755050624}, {"country_id": "AL", "probability": 0.07968965780401148}]}
{"name": "renaud", "country": [{"country_id": "BJ", "probability": 0.2334374831795115}, {"country_id": "BE", "probability": 0.2014852071788965}, {"country_id": "FR", "probability": 0.17038842826505884}]}
{"name": "renaudlise", "country": []}
{"name": "renbin", "country": []}
{"name": "renbing", "country": []}
{"name": "renchang", "country": []}
{"name": "rencheng", "country": []}
{"name": "renchu", "country": []}
{"name": "renchuen", "country": []}
{"name": "rendar", "country": []}
{"name": "rende", "country": []}
{"name": "rendely", "country": []}
{"name": "rendi", "country": [{"country_id": "ID", "probability": 1}]}
{"name": "rendy", "country": [{"country_id": "ID", "probability": 0.9145718846124808}, {"country_id": "CZ", "probability": 0.06617733435428048}, {"country_id": "NL", "probability": 0.016594606881704763}]}
{"name": "rene", "country": [{"country_id": "SV", "probability": 0.12597468453432942}, {"country_id": "AT", "probability": 0.09740681339143796}, {"country_id": "DK", "probability": 0.08480586601993112}]}
{"name": "renee", "country": [{"country_id": "AU", "probability": 0.13363726748330662}, {"country_id": "US", "probability": 0.13309181735770748}, {"country_id": "TW", "probability": 0.1150678200564382}]}
{"name": "reneemarie", "country": []}
{"name": "renelise", "country": []}
{"name": "renelson", "country": []}
{"name": "reneta", "country": [{"country_id": "BG", "probability": 1}]}
{"name": "renfa", "country": []}
{"name": "renfeng", "country": []}
{"name": "reng", "country": []}
{"name": "rengarajan", "country": []}
{"name": "rengga", "country": [{"country_id": "ID", "probability": 1}]}
{"name": "rengin", "country": [{"country_id": "TR", "probability": 1}]}
{"name": "renhe", "country": []}
{"name": "renhong", "country": []}
{"name": "renhua", "country": []}
{"name": "renhuai", "country": []}
{"name": "renhuan", "country": []}
{"name": "renhui", "country": []}
{"name": "renhung", "country": []}
{"name": "renia", "country": [{"country_id": "PL", "probability": 0.5775377873190588}, {"country_id": "GR", "probability": 0.3832425201725811}, {"country_id": "GB", "probability": 0.022712794614977785}]}
{"name": "reniel", "country": [{"country_id": "PH", "probability": 1}]}
{"name": "renier", "country": [{"country_id": "ZA", "probability": 0.8443823792849615}, {"country_id": "PH", "probability": 0.14912659628749647}, {"country_id": "FR", "probability": 0.006491024427542047}]}
{"name": "renilda", "country": []}
{"name": "renita", "country": [{"country_id": "ID", "probability": 0.8049336029379216}, {"country_id": "PH", "probability": 0.19506639706207832}]}
{"name": "renjian", "country": []}
{"name": "renjiang", "country": []}
{"name": "renjie", "country": []}
{"name": "renjith", "country": [{"country_id": "IN", "probability": 1}]}
{"name": "renjun", "country": []}
{"name": "renke", "country": [{"country_id": "DE", "probability": 1}]}
{"name": "renkuan", "country": []}
{"name": "renliang", "country": []}
{"name": "renlong", "country": []}
{"name": "renming", "country": []}
{"name": "renmou", "country": []}
{"name": "renmu", "country": []}
{"name": "renn", "country": []}
{"name": "rennaly", "country": []}
{"name": "rennie", "country": [{"country_id": "NL", "probability": 0.47541518408918065}, {"country_id": "PH", "probability": 0.3204378611525677}, {"country_id": "GB", "probability": 0.20414695475825162}]}
{"name": "rennong", "country": []}
{"name": "renny", "country": [{"country_id": "VE", "probability": 0.4919318181914344}, {"country_id": "ID", "probability": 0.46127048755248595}, {"country_id": "IT", "probability": 0.02422309651560266}]}
{"name": "reno", "country": [{"country_id": "ID", "probability": 0.3284790476271413}, {"country_id": "SA", "probability": 0.11114230452482184}, {"country_id": "SK", "probability": 0.08150352646419914}]}
{"name": "renold", "country": []}
{"name": "renos", "country": [{"country_id": "CY", "probability": 0.8119329630101414}, {"country_id": "GR", "probability": 0.18806703698985866}]}
{"name": "renquan", "country": []}
{"name": "renren", "country": []}
{"name": "rens", "country": [{"country_id": "NL", "probability": 0.9336137247706868}, {"country_id": "BE", "probability": 0.059591716690527756}, {"country_id": "FR", "probability": 0.006794558538785369}]}
{"name": "rense", "country": [{"country_id": "NL", "probability": 1}]}
{"name": "renske", "country": [{"country_id": "NL", "probability": 1}]}
{"name": "rensong", "country": []}
{"name": "rentao", "country": []}
{"name": "renu", "country": [{"country_id": "IN", "probability": 0.8112353062531532}, {"country_id": "TH", "probability": 0.18876469374684682}]}
{"name": "renuga", "country": [{"country_id": "MY", "probability": 1}]}
{"name": "renuka", "country": [{"country_id": "IN", "probability": 0.7555417883733605}, {"country_id": "MY", "probability": 0.24445821162663944}]}
{"name": "renukswamy", "country": []}
{"name": "renushree", "country": []}
{"name": "renwang", "country": []}
{"name": "renwen", "country": []}
{"name": "renwhei", "country": []}
{"name": "renwu", "country": []}
{"name": "renxi", "country": []}
{"name": "renxian", "country": []}
{"name": "renxiang", "country": []}
{"name": "reny", "country": [{"country_id": "ID", "probability": 0.6695873202044111}, {"country_id": "CZ", "probability": 0.12931830338226213}, {"country_id": "HU", "probability": 0.0858903264592642}]}
{"name": "renyan", "country": []}
{"name": "renyu", "country": []}
{"name": "renyuan", "country": []}
{"name": "renz", "country": [{"country_id": "PH", "probability": 0.9600733481390077}, {"country_id": "NL", "probability": 0.03992665186099227}]}
{"name": "renzo", "country": [{"country_id": "PE", "probability": 0.5484831146191244}, {"country_id": "AR", "probability": 0.1069792925938131}, {"country_id": "IT", "probability": 0.08817072543855971}]}
{"name": "repast", "country": []}
{"name": "repecka", "country": []}
{"name": "rephael", "country": []}
{"name": "rere", "country": [{"country_id": "SD", "probability": 0.4504106351107851}, {"country_id": "JO", "probability": 0.17692815933749706}, {"country_id": "EG", "probability": 0.15059927983415922}]}
{"name": "rerum", "country": []}
{"name": "resban", "country": []}
{"name": "researcher", "country": []}
{"name": "reseaux", "country": []}
{"name": "reshan", "country": []}
{"name": "reshef", "country": []}
{"name": "reshma", "country": [{"country_id": "MU", "probability": 0.664682228013303}, {"country_id": "IN", "probability": 0.2870356328267235}, {"country_id": "NL", "probability": 0.037381354174806286}]}
{"name": "reshmi", "country": [{"country_id": "IN", "probability": 1}]}
{"name": "reshu", "country": [{"country_id": "IN", "probability": 1}]}
{"name": "resit", "country": [{"country_id": "TR", "probability": 0.6634629486754255}, {"country_id": "DE", "probability": 0.3365370513245745}]}
{"name": "resmana", "country": []}
{"name": "resmiati", "country": []}
{"name": "resta", "country": []}
{"name": "resti", "country": [{"country_id": "ID", "probability": 0.9891530859528376}, {"country_id": "ES", "probability": 0.010846914047162396}]}
{"name": "restiyana", "country": []}
{"name": "resul", "country": [{"country_id": "TR", "probability": 0.3765552297852653}, {"country_id": "MK", "probability": 0.24095973569064252}, {"country_id": "AZ", "probability": 0.22676833453459833}]}
{"name": "retha", "country": [{"country_id": "ZA", "probability": 0.8524403893527668}, {"country_id": "ID", "probability": 0.1475596106472331}]}
{"name": "retna", "country": [{"country_id": "ID", "probability": 1}]}
{"name": "retno", "country": [{"country_id": "ID", "probability": 1}]}
{"name": "reto", "country": [{"country_id": "CH", "probability": 0.9932738301132834}, {"country_id": "DE", "probability": 0.0044742765659494515}, {"country_id": "ES", "probability": 0.002251893320767215}]}
{"name": "retta", "country": []}
{"name": "reuben", "country": [{"country_id": "KE", "probability": 0.2565735807409796}, {"country_id": "MT", "probability": 0.23642826140133238}, {"country_id": "TZ", "probability": 0.173982597156776}]}
{"name": "reubens", "country": []}
{"name": "reuber", "country": []}
{"name": "reuching", "country": []}
{"name": "reuel", "country": [{"country_id": "PH", "probability": 1}]}
{"name": "reuma", "country": []}
{"name": "reut", "country": [{"country_id": "IL", "probability": 1}]}
{"name": "reuven", "country": [{"country_id": "IL", "probability": 0.9999999999999999}]}
{"name": "rev", "country": [{"country_id": "NG", "probability": 0.7311748889521779}, {"country_id": "GB", "probability": 0.17056543459777207}, {"country_id": "IT", "probability": 0.05677343483576335}]}
{"name": "reva", "country": [{"country_id": "ID", "probability": 0.9464033676670094}, {"country_id": "TR", "probability": 0.05359663233299056}]}
{"name": "revathy", "country": [{"country_id": "MY", "probability": 0.6359518605592176}, {"country_id": "IN", "probability": 0.36404813944078235}]}
{"name": "revati", "country": []}
{"name": "revinson", "country": []}
{"name": "revised", "country": []}
{"name": "revista", "country": []}
{"name": "revital", "country": [{"country_id": "IL", "probability": 1}]}
{"name": "rewa", "country": []}
{"name": "rewai", "country": []}
{"name": "rex", "country": [{"country_id": "TW", "probability": 0.25051273101998517}, {"country_id": "HK", "probability": 0.1708078855989211}, {"country_id": "PH", "probability": 0.16898421829283478}]}
{"name": "rey", "country": [{"country_id": "PH", "probability": 0.34309155750452425}, {"country_id": "VE", "probability": 0.11293773713494427}, {"country_id": "DO", "probability": 0.10760924224780277}]}
{"name": "reyad", "country": [{"country_id": "DZ", "probability": 1}]}
{"name": "reyes", "country": [{"country_id": "ES", "probability": 0.5409452710269794}, {"country_id": "MX", "probability": 0.3006317429858633}, {"country_id": "PH", "probability": 0.0955725841159553}]}
{"name": "reyhan", "country": [{"country_id": "TR", "probability": 0.2850660988928263}, {"country_id": "BG", "probability": 0.27483504280139576}, {"country_id": "AZ", "probability": 0.16859451072962542}]}
{"name": "reyhane", "country": [{"country_id": "IR", "probability": 1}]}
{"name": "reyk", "country": []}
{"name": "reymond", "country": [{"country_id": "PH", "probability": 0.9932214099166976}, {"country_id": "FR", "probability": 0.006778590083302433}]}
{"name": "reyn", "country": []}
{"name": "reyna", "country": [{"country_id": "MX", "probability": 0.372951012659123}, {"country_id": "DO", "probability": 0.31973149195534084}, {"country_id": "PE", "probability": 0.16377438678542905}]}
{"name": "reynal", "country": []}
{"name": "reynald", "country": [{"country_id": "PH", "probability": 0.7135464981185602}, {"country_id": "FR", "probability": 0.28645350188143975}]}
{"name": "reynaldi", "country": []}
{"name": "reynaldo", "country": [{"country_id": "BO", "probability": 0.32360737232678405}, {"country_id": "PH", "probability": 0.3063694241792685}, {"country_id": "DO", "probability": 0.14928661509058738}]}
{"name": "reynaldorivera", "country": []}
{"name": "reynilda", "country": []}
{"name": "reynol", "country": []}
{"name": "reynold", "country": [{"country_id": "PH", "probability": 0.6424999770090709}, {"country_id": "ID", "probability": 0.2832596297601658}, {"country_id": "US", "probability": 0.07424039323076329}]}
{"name": "reys", "country": []}
{"name": "reyyan", "country": [{"country_id": "TR", "probability": 1}]}
{"name": "reza", "country": [{"country_id": "IR", "probability": 0.7238756366719781}, {"country_id": "ID", "probability": 0.06179408124491857}, {"country_id": "BD", "probability": 0.044055509744592755}]}
{"name": "rezaei", "country": []}
{"name": "rezaie", "country": []}
{"name": "rezan", "country": [{"country_id": "TR", "probability": 0.67407588484643}, {"country_id": "DE", "probability": 0.32592411515357}]}
{"name": "rezarta", "country": [{"country_id": "AL", "probability": 0.9914911863346461}, {"country_id": "IT", "probability": 0.008508813665353778}]}
{"name": "rezaul", "country": [{"country_id": "BD", "probability": 1}]}
{"name": "rezaur", "country": []}
{"name": "reze", "country": []}
{"name": "rezeda", "country": [{"country_id": "RU", "probability": 1}]}
{"name": "reziwanguli", "country": []}
{"name": "rezvan", "country": [{"country_id": "IR", "probability": 1}]}
{"name": "rezvaneh", "country": []}
{"name": "rezwanal", "country": []}
{"name": "rezwanur", "country": []}
{"name": "rhandley", "country": []}
{"name": "rhea", "country": [{"country_id": "PH", "probability": 0.8754017821894585}, {"country_id": "SG", "probability": 0.08057122546792794}, {"country_id": "IN", "probability": 0.028906132122565768}]}
{"name": "rheba", "country": []}
{"name": "rhee", "country": []}
{"name": "rhen", "country": [{"country_id": "PH", "probability": 1.0000000000000002}]}
{"name": "rhett", "country": [{"country_id": "US", "probability": 1.0000000000000002}]}
{"name": "rhew", "country": []}
{"name": "rhian", "country": [{"country_id": "GB", "probability": 0.7009044126703868}, {"country_id": "PH", "probability": 0.299095587329613}]}
{"name": "rhiann", "country": []}
{"name": "rhiannon", "country": [{"country_id": "GB", "probability": 1}]}
{"name": "rhidian", "country": []}
{"name": "rhiki", "country": []}
{"name": "rhim", "country": []}
{"name": "rhine", "country": [{"country_id": "PH", "probability": 1}]}
{"name": "rhio", "country": [{"country_id": "PH", "probability": 1}]}
{"name": "rhishi", "country": []}
{"name": "rhitankar", "country": []}
{"name": "rhjm", "country": []}
{"name": "rho", "country": [{"country_id": "IT", "probability": 0.5548238468910238}, {"country_id": "FR", "probability": 0.44517615310897624}]}
{"name": "rhoda", "country": [{"country_id": "GH", "probability": 0.3082576714324892}, {"country_id": "KE", "probability": 0.2762381659659883}, {"country_id": "PH", "probability": 0.2519175424716237}]}
{"name": "rhodora", "country": [{"country_id": "PH", "probability": 1}]}
{"name": "rhodri", "country": [{"country_id": "GB", "probability": 1}]}
{"name": "rhona", "country": [{"country_id": "PH", "probability": 0.8002744539658114}, {"country_id": "GB", "probability": 0.19972554603418868}]}
{"name": "rhonan", "country": []}
{"name": "rhonda", "country": [{"country_id": "US", "probability": 0.496756662059578}, {"country_id": "CA", "probability": 0.45004304590884736}, {"country_id": "GB", "probability": 0.04780713466956569}]}
{"name": "rhondda", "country": []}
{"name": "rhonwen", "country": []}
{"name": "rhoshel", "country": []}
{"name": "rhouma", "country": [{"country_id": "TN", "probability": 1}]}
{"name": "rhys", "country": [{"country_id": "AU", "probability": 0.6626420597115781}, {"country_id": "GB", "probability": 0.320239299657942}, {"country_id": "PH", "probability": 0.017118640630479985}]}
{"name": "rhythm", "country": []}
{"name": "ri", "country": [{"country_id": "JP", "probability": 0.2556807663558528}, {"country_id": "KR", "probability": 0.21012769624248606}, {"country_id": "ID", "probability": 0.11318267266221584}]}
{"name": "ria", "country": [{"country_id": "ID", "probability": 0.222431483290835}, {"country_id": "NL", "probability": 0.19097488351314765}, {"country_id": "GR", "probability": 0.13383891781002877}]}
{"name": "riaan", "country": [{"country_id": "ZA", "probability": 1}]}
{"name": "riad", "country": [{"country_id": "DZ", "probability": 0.4749992566757083}, {"country_id": "LB", "probability": 0.13168078052563653}, {"country_id": "AZ", "probability": 0.08382965032103629}]}
{"name": "riadh", "country": [{"country_id": "TN", "probability": 0.8053094387316341}, {"country_id": "DZ", "probability": 0.13126210674853575}, {"country_id": "CA", "probability": 0.04262139326853576}]}
{"name": "riahinia", "country": []}
{"name": "riajeng", "country": []}
{"name": "rialantonio", "country": []}
{"name": "rialize", "country": []}
{"name": "rian", "country": [{"country_id": "ID", "probability": 0.6845876533907514}, {"country_id": "NL", "probability": 0.12125626141343014}, {"country_id": "ZA", "probability": 0.07968697488615385}]}
{"name": "riana", "country": [{"country_id": "MG", "probability": 0.5865158456507767}, {"country_id": "ZA", "probability": 0.20104105287523844}, {"country_id": "ID", "probability": 0.1656103980951013}]}
{"name": "rianka", "country": []}
{"name": "riann", "country": []}
{"name": "rianne", "country": [{"country_id": "NL", "probability": 0.9423551724915983}, {"country_id": "PH", "probability": 0.029890037520662834}, {"country_id": "BE", "probability": 0.015242845497413733}]}
{"name": "rianon", "country": []}
{"name": "riat", "country": []}
{"name": "riaz", "country": [{"country_id": "PK", "probability": 0.5423306029448225}, {"country_id": "BD", "probability": 0.33905026381983183}, {"country_id": "ZA", "probability": 0.05170635023981241}]}
{"name": "riazudin", "country": []}
{"name": "riba", "country": []}
{"name": "ribamar", "country": []}
{"name": "ribeiro", "country": [{"country_id": "LU", "probability": 0.3147196639613811}, {"country_id": "MZ", "probability": 0.24638055740048512}, {"country_id": "PT", "probability": 0.21857160534324152}]}
{"name": "ric", "country": [{"country_id": "RE", "probability": 0.18624470384167519}, {"country_id": "FR", "probability": 0.13418822636487193}, {"country_id": "PH", "probability": 0.08994366069943052}]}
{"name": "rica", "country": [{"country_id": "PH", "probability": 0.3481102904649564}, {"country_id": "BR", "probability": 0.16265246396728783}, {"country_id": "PT", "probability": 0.10409221140316331}]}
{"name": "ricard", "country": [{"country_id": "ES", "probability": 0.6833801228167907}, {"country_id": "SE", "probability": 0.17011117557883748}, {"country_id": "PT", "probability": 0.0820152715122188}]}
{"name": "ricarda", "country": [{"country_id": "DE", "probability": 0.6921042046338232}, {"country_id": "AT", "probability": 0.2561391387994785}, {"country_id": "PT", "probability": 0.04208069857340699}]}
{"name": "ricardo", "country": [{"country_id": "PT", "probability": 0.11358257315207183}, {"country_id": "BR", "probability": 0.060970749995996665}, {"country_id": "PA", "probability": 0.05004248917553854}]}
{"name": "ricardoadan", "country": []}
{"name": "ricaurte", "country": []}
{"name": "ricca", "country": [{"country_id": "ID", "probability": 0.5402391880703309}, {"country_id": "PH", "probability": 0.24019950068439258}, {"country_id": "IT", "probability": 0.2195613112452765}]}
{"name": "riccardo", "country": [{"country_id": "IT", "probability": 0.652221320474561}, {"country_id": "", "probability": 0.15696975054666495}, {"country_id": "CH", "probability": 0.06614781696483467}]}
{"name": "ricco", "country": [{"country_id": "ID", "probability": 0.2172854495919575}, {"country_id": "CH", "probability": 0.2169964899971156}, {"country_id": "DE", "probability": 0.17618971874685393}]}
{"name": "rice", "country": [{"country_id": "CN", "probability": 0.9265385156106468}, {"country_id": "FR", "probability": 0.07346148438935313}]}
{"name": "rich", "country": [{"country_id": "GB", "probability": 0.25746250876529614}, {"country_id": "US", "probability": 0.14424010982575813}, {"country_id": "GH", "probability": 0.12126503132985109}]}
{"name": "richa", "country": [{"country_id": "IN", "probability": 0.8787945333840089}, {"country_id": "ID", "probability": 0.11316205388012182}, {"country_id": "ES", "probability": 0.008043412735869313}]}
{"name": "richang", "country": []}
{"name": "richard", "country": [{"country_id": "US", "probability": 0.05700851680361088}, {"country_id": "NZ", "probability": 0.053016481679035096}, {"country_id": "GH", "probability": 0.04569858266399526}]}
{"name": "richardson", "country": [{"country_id": "GH", "probability": 0.5544067214894204}, {"country_id": "NG", "probability": 0.17673141098220596}, {"country_id": "PH", "probability": 0.12367885710680694}]}
{"name": "richarth", "country": []}
{"name": "richele", "country": []}
{"name": "richelle", "country": [{"country_id": "PH", "probability": 0.7822236999803713}, {"country_id": "SG", "probability": 0.10985675397118431}, {"country_id": "NL", "probability": 0.08921329146074213}]}
{"name": "richeng", "country": []}
{"name": "richi", "country": [{"country_id": "PE", "probability": 0.28009537666910417}, {"country_id": "AT", "probability": 0.2231982003913552}, {"country_id": "ES", "probability": 0.1162659098786288}]}
{"name": "richie", "country": [{"country_id": "IE", "probability": 0.2056468708186422}, {"country_id": "GH", "probability": 0.1767942723896879}, {"country_id": "UG", "probability": 0.08956261919611803}]}
{"name": "richman", "country": [{"country_id": "NG", "probability": 1}]}
{"name": "richmond", "country": [{"country_id": "GH", "probability": 0.7302019709305709}, {"country_id": "CI", "probability": 0.15235830383080573}, {"country_id": "PH", "probability": 0.054470859183637324}]}
{"name": "richong", "country": []}
{"name": "rick", "country": [{"country_id": "NL", "probability": 0.18689509894625142}, {"country_id": "CA", "probability": 0.14365207208274963}, {"country_id": "US", "probability": 0.12164910153039415}]}
{"name": "rickard", "country": [{"country_id": "SE", "probability": 1}]}
{"name": "rickey", "country": [{"country_id": "US", "probability": 1}]}
{"name": "ricki", "country": [{"country_id": "DK", "probability": 0.34526115286616255}, {"country_id": "ID", "probability": 0.267136619985947}, {"country_id": "CH", "probability": 0.11309705739642922}]}
{"name": "rickie", "country": [{"country_id": "US", "probability": 0.6642536053997832}, {"country_id": "GB", "probability": 0.3357463946002169}]}
{"name": "rickson", "country": [{"country_id": "PH", "probability": 1}]}
{"name": "ricky", "country": [{"country_id": "HK", "probability": 0.14532027660214114}, {"country_id": "NZ", "probability": 0.09207807827415974}, {"country_id": "ID", "probability": 0.07157740701971997}]}
{"name": "rico", "country": [{"country_id": "NL", "probability": 0.12751544623518446}, {"country_id": "DE", "probability": 0.11488488617835257}, {"country_id": "ID", "probability": 0.09186311942089873}]}
{"name": "ricojuan", "country": []}
{"name": "rida", "country": [{"country_id": "DZ", "probability": 0.25182331766301747}, {"country_id": "MA", "probability": 0.23733895528606375}, {"country_id": "LB", "probability": 0.18623824740860445}]}
{"name": "riddhi", "country": [{"country_id": "IN", "probability": 1}]}
{"name": "ridha", "country": [{"country_id": "TN", "probability": 0.809197108236233}, {"country_id": "DZ", "probability": 0.11401937821101306}, {"country_id": "ID", "probability": 0.05942079507338552}]}
{"name": "ridhi", "country": [{"country_id": "IN", "probability": 1}]}
{"name": "ridho", "country": [{"country_id": "ID", "probability": 1}]}
{"name": "ridi", "country": [{"country_id": "AL", "probability": 0.9877391824714239}, {"country_id": "IT", "probability": 0.0122608175285762}]}
{"name": "ridik", "country": []}
{"name": "ridley", "country": []}
{"name": "ridong", "country": []}
{"name": "ridsdale", "country": []}
{"name": "ridvan", "country": [{"country_id": "MK", "probability": 0.4743959040757886}, {"country_id": "AL", "probability": 0.1790647339473882}, {"country_id": "TR", "probability": 0.12658226224361388}]}
{"name": "ridwan", "country": [{"country_id": "ID", "probability": 0.7199121870524242}, {"country_id": "NG", "probability": 0.15319423811776844}, {"country_id": "SG", "probability": 0.0526648505976443}]}
{"name": "ridza", "country": []}
{"name": "rie", "country": [{"country_id": "JP", "probability": 0.7620045385447463}, {"country_id": "DK", "probability": 0.17546664141482007}, {"country_id": "ID", "probability": 0.03395226357584062}]}
{"name": "riedl", "country": []}
{"name": "rieko", "country": [{"country_id": "JP", "probability": 1}]}
{"name": "riemann", "country": []}
{"name": "rien", "country": [{"country_id": "NL", "probability": 0.2970426431759912}, {"country_id": "FR", "probability": 0.15548253425371786}, {"country_id": "DZ", "probability": 0.14850419018554661}]}
{"name": "rifaht", "country": []}
{"name": "rifat", "country": [{"country_id": "AL", "probability": 0.41941270182915935}, {"country_id": "TR", "probability": 0.24053777568880338}, {"country_id": "RS", "probability": 0.11943607150729481}]}
{"name": "rifka", "country": [{"country_id": "ID", "probability": 1}]}
{"name": "rifkin", "country": []}
{"name": "rifky", "country": [{"country_id": "ID", "probability": 1}]}
{"name": "rigas", "country": [{"country_id": "GR", "probability": 1}]}
{"name": "rigbe", "country": []}
{"name": "righy", "country": []}
{"name": "rigoberto", "country": [{"country_id": "MX", "probability": 0.4357152892802869}, {"country_id": "DO", "probability": 0.33950933244389825}, {"country_id": "AO", "probability": 0.15335846107978449}]}
{"name": "rihab", "country": [{"country_id": "TN", "probability": 0.6124429093247155}, {"country_id": "MA", "probability": 0.2199635134677264}, {"country_id": "LB", "probability": 0.0964094203631742}]}
{"name": "riheb", "country": []}
{"name": "rihem", "country": [{"country_id": "TN", "probability": 0.8732212774342133}, {"country_id": "DZ", "probability": 0.1267787225657866}]}
{"name": "riheng", "country": []}
{"name": "riho", "country": [{"country_id": "EE", "probability": 0.8971906182795283}, {"country_id": "JP", "probability": 0.10280938172047172}]}
{"name": "rihua", "country": []}
{"name": "rihui", "country": []}
{"name": "riikka", "country": [{"country_id": "FI", "probability": 0.9890004485101898}, {"country_id": "", "probability": 0.010999551489810194}]}
{"name": "riina", "country": [{"country_id": "EE", "probability": 0.5745211557493128}, {"country_id": "FI", "probability": 0.4183681505485622}, {"country_id": "", "probability": 0.005358986866368277}]}
{"name": "riitta", "country": [{"country_id": "FI", "probability": 0.9603589244882877}, {"country_id": "SE", "probability": 0.027130881459777538}, {"country_id": "", "probability": 0.01251019405193471}]}
{"name": "riittaliisa", "country": []}
{"name": "riivo", "country": []}
{"name": "rija", "country": [{"country_id": "MG", "probability": 0.9991810114781119}, {"country_id": "FR", "probability": 0.000818988521888131}]}
{"name": "rijavec", "country": []}
{"name": "riji", "country": []}
{"name": "rijk", "country": [{"country_id": "NL", "probability": 1}]}
{"name": "rijn", "country": []}
{"name": "rijnsoever", "country": []}
{"name": "rijurekha", "country": []}
{"name": "rik", "country": [{"country_id": "NL", "probability": 0.565487356949828}, {"country_id": "BE", "probability": 0.275962815580417}, {"country_id": "GB", "probability": 0.04742679249779231}]}
{"name": "rika", "country": [{"country_id": "ID", "probability": 0.402334526152195}, {"country_id": "JP", "probability": 0.38452515373946466}, {"country_id": "ZA", "probability": 0.06526088625061041}]}
{"name": "rikam", "country": []}
{"name": "rikard", "country": [{"country_id": "SE", "probability": 0.868375480685395}, {"country_id": "NO", "probability": 0.12837111962986072}, {"country_id": "ES", "probability": 0.003253399684744252}]}
{"name": "rikerdy", "country": []}
{"name": "rikesh", "country": []}
{"name": "riki", "country": [{"country_id": "MK", "probability": 0.3154397730804732}, {"country_id": "ID", "probability": 0.139569667581956}, {"country_id": "AL", "probability": 0.08085446730660356}]}
{"name": "rikin", "country": []}
{"name": "rikinorhakis", "country": []}
{"name": "rikio", "country": []}
{"name": "rikke", "country": [{"country_id": "DK", "probability": 0.9283113566413292}, {"country_id": "", "probability": 0.03880791300291218}, {"country_id": "NO", "probability": 0.03288073035575856}]}
{"name": "rikki", "country": [{"country_id": "GB", "probability": 0.5356165403892207}, {"country_id": "ID", "probability": 0.2827581676434681}, {"country_id": "US", "probability": 0.16417985753853856}]}
{"name": "riko", "country": [{"country_id": "ID", "probability": 0.46199688604363004}, {"country_id": "JP", "probability": 0.2875298078117912}, {"country_id": "TN", "probability": 0.08498828384745569}]}
{"name": "riktesh", "country": []}
{"name": "riku", "country": [{"country_id": "FI", "probability": 0.922755969865608}, {"country_id": "JP", "probability": 0.0678643872481612}, {"country_id": "", "probability": 0.008353431984469977}]}
{"name": "rilene", "country": []}
{"name": "riley", "country": [{"country_id": "CA", "probability": 0.5553314174216292}, {"country_id": "US", "probability": 0.2841924740039413}, {"country_id": "GB", "probability": 0.14470386203076324}]}
{"name": "rilva", "country": []}
{"name": "rim", "country": [{"country_id": "TN", "probability": 0.47739592927489055}, {"country_id": "MA", "probability": 0.2132139260974173}, {"country_id": "LB", "probability": 0.15916542004547996}]}
{"name": "rima", "country": [{"country_id": "LT", "probability": 0.3750752163268256}, {"country_id": "LB", "probability": 0.17013193618937295}, {"country_id": "TN", "probability": 0.07931954370740148}]}
{"name": "rimanta", "country": []}
{"name": "rimantas", "country": [{"country_id": "LT", "probability": 0.9952346644541806}, {"country_id": "GB", "probability": 0.004765335545819317}]}
{"name": "rimante", "country": [{"country_id": "LT", "probability": 1}]}
{"name": "rimas", "country": [{"country_id": "LT", "probability": 0.9565215510791751}, {"country_id": "DZ", "probability": 0.025958499865550017}, {"country_id": "MA", "probability": 0.012635072700309098}]}
{"name": "riming", "country": []}
{"name": "rimli", "country": []}
{"name": "rimon", "country": [{"country_id": "EG", "probability": 0.5584151605046518}, {"country_id": "SE", "probability": 0.39136471522071864}, {"country_id": "DE", "probability": 0.05022012427462954}]}
{"name": "rimsarah", "country": []}
{"name": "rina", "country": [{"country_id": "MG", "probability": 0.19140226747284594}, {"country_id": "ID", "probability": 0.16717795990767756}, {"country_id": "JP", "probability": 0.10695534973586017}]}
{"name": "rinaldi", "country": [{"country_id": "ID", "probability": 0.9643879404575934}, {"country_id": "IT", "probability": 0.03561205954240668}]}
{"name": "rinaldo", "country": [{"country_id": "NL", "probability": 0.28024255811807514}, {"country_id": "IT", "probability": 0.23387806776975795}, {"country_id": "CH", "probability": 0.20188285616145094}]}
{"name": "rinat", "country": [{"country_id": "KZ", "probability": 0.5512489112613156}, {"country_id": "IL", "probability": 0.18107375734303027}, {"country_id": "AZ", "probability": 0.16739481092891334}]}
{"name": "rincon", "country": [{"country_id": "ES", "probability": 0.9999999999999999}]}
{"name": "rincy", "country": []}
{"name": "rincymedayil", "country": []}
{"name": "rindang", "country": [{"country_id": "ID", "probability": 1}]}
{"name": "rindha", "country": []}
{"name": "rindra", "country": [{"country_id": "MG", "probability": 1}]}
{"name": "rineke", "country": [{"country_id": "NL", "probability": 1}]}
{"name": "rinel", "country": []}
{"name": "ringa", "country": []}
{"name": "ringger", "country": []}
{"name": "ringo", "country": [{"country_id": "HK", "probability": 0.6139359351308287}, {"country_id": "BE", "probability": 0.0748924056592237}, {"country_id": "DE", "probability": 0.07427576787117376}]}
{"name": "rini", "country": [{"country_id": "ID", "probability": 0.867394508754319}, {"country_id": "NL", "probability": 0.06189154539493953}, {"country_id": "IN", "probability": 0.033648712406552185}]}
{"name": "rinichiro", "country": []}
{"name": "rinie", "country": [{"country_id": "NL", "probability": 0.6516792724533202}, {"country_id": "ID", "probability": 0.34832072754667975}]}
{"name": "rinita", "country": []}
{"name": "rinkaj", "country": []}
{"name": "rinkesh", "country": [{"country_id": "IN", "probability": 1}]}
{"name": "rinkita", "country": []}
{"name": "rinkle", "country": []}
{"name": "rinku", "country": [{"country_id": "IN", "probability": 1}]}
{"name": "rinni", "country": []}
{"name": "rino", "country": [{"country_id": "IT", "probability": 0.414405570228112}, {"country_id": "ID", "probability": 0.16745610339208095}, {"country_id": "JP", "probability": 0.09773693778612637}]}
{"name": "rinske", "country": [{"country_id": "NL", "probability": 0.9999999999999999}]}
{"name": "rinta", "country": []}
{"name": "rintaro", "country": [{"country_id": "JP", "probability": 1}]}
{"name": "rinto", "country": [{"country_id": "ID", "probability": 1}]}
{"name": "rio", "country": [{"country_id": "ID", "probability": 0.4917445227907061}, {"country_id": "PH", "probability": 0.10658587289568937}, {"country_id": "JP", "probability": 0.09175726836572975}]}
{"name": "riofrio", "country": []}
{"name": "rion", "country": [{"country_id": "FR", "probability": 1}]}
{"name": "rios", "country": [{"country_id": "ES", "probability": 0.3598484968100311}, {"country_id": "FR", "probability": 0.3571156489221073}, {"country_id": "IT", "probability": 0.28303585426786154}]}
{"name": "rioseco", "country": []}
{"name": "ripei", "country": []}
{"name": "ripeng", "country": []}
{"name": "ripon", "country": [{"country_id": "BD", "probability": 0.9936212271442444}, {"country_id": "GB", "probability": 0.006378772855755557}]}
{"name": "riqi", "country": []}
{"name": "riqing", "country": []}
{"name": "riqui", "country": [{"country_id": "ES", "probability": 1}]}
{"name": "riri", "country": [{"country_id": "MG", "probability": 0.23637450290354714}, {"country_id": "ID", "probability": 0.16718509234515058}, {"country_id": "TN", "probability": 0.16292609972114241}]}
{"name": "ris", "country": [{"country_id": "ID", "probability": 0.49962676524533056}, {"country_id": "PT", "probability": 0.39896250593538796}, {"country_id": "ES", "probability": 0.04128151529418476}]}
{"name": "risa", "country": [{"country_id": "JP", "probability": 0.7106559880307556}, {"country_id": "ID", "probability": 0.16761830176531067}, {"country_id": "TH", "probability": 0.0688023416768665}]}
{"name": "risala", "country": []}
{"name": "risan", "country": []}
{"name": "rischan", "country": []}
{"name": "riselis", "country": []}
{"name": "rish", "country": [{"country_id": "IN", "probability": 0.865943954610223}, {"country_id": "GB", "probability": 0.13405604538977697}]}
{"name": "risha", "country": [{"country_id": "ID", "probability": 0.6012303427902361}, {"country_id": "RU", "probability": 0.3987696572097639}]}
{"name": "rishab", "country": [{"country_id": "IN", "probability": 1}]}
{"name": "rishabh", "country": [{"country_id": "IN", "probability": 1}]}
{"name": "rishan", "country": []}
{"name": "rishav", "country": [{"country_id": "IN", "probability": 1}]}
{"name": "rishee", "country": []}
{"name": "rishemjit", "country": []}
{"name": "risheng", "country": []}
{"name": "rishi", "country": [{"country_id": "MU", "probability": 0.5319233702105648}, {"country_id": "IN", "probability": 0.41955286863753016}, {"country_id": "NL", "probability": 0.0179037166018057}]}
{"name": "rishija", "country": []}
{"name": "rishika", "country": []}
{"name": "rishikesh", "country": [{"country_id": "IN", "probability": 1.0000000000000002}]}
{"name": "rishiraj", "country": [{"country_id": "IN", "probability": 1}]}
{"name": "rishon", "country": []}
{"name": "risi", "country": [{"country_id": "ES", "probability": 1}]}
{"name": "riska", "country": [{"country_id": "ID", "probability": 1}]}
{"name": "riski", "country": [{"country_id": "ID", "probability": 1}]}
{"name": "risky", "country": [{"country_id": "ID", "probability": 1}]}
{"name": "risma", "country": [{"country_id": "ID", "probability": 1}]}
{"name": "risnawati", "country": []}
{"name": "rispah", "country": []}
{"name": "riste", "country": [{"country_id": "MK", "probability": 1}]}
{"name": "risth", "country": []}
{"name": "risto", "country": [{"country_id": "FI", "probability": 0.47827826019237885}, {"country_id": "EE", "probability": 0.3137914572472249}, {"country_id": "MK", "probability": 0.13985640462027682}]}
{"name": "risul", "country": []}
{"name": "riswandha", "country": []}
{"name": "riswanti", "country": []}
{"name": "rit", "country": [{"country_id": "TH", "probability": 0.8347763954904266}, {"country_id": "BE", "probability": 0.14338369824530792}, {"country_id": "IT", "probability": 0.021839906264265355}]}
{"name": "rita", "country": [{"country_id": "NU", "probability": 0.603473426670529}, {"country_id": "SL", "probability": 0.0736461388489024}, {"country_id": "LT", "probability": 0.035856956476883736}]}
{"name": "ritabrata", "country": []}
{"name": "ritah", "country": [{"country_id": "UG", "probability": 1}]}
{"name": "ritam", "country": []}
{"name": "ritankar", "country": []}
{"name": "ritaumaria", "country": []}
{"name": "ritch", "country": [{"country_id": "FR", "probability": 1}]}
{"name": "ritchie", "country": [{"country_id": "PH", "probability": 0.5112179812138903}, {"country_id": "NL", "probability": 0.21133689976573017}, {"country_id": "GB", "probability": 0.10393555187961168}]}
{"name": "ritesh", "country": [{"country_id": "MU", "probability": 0.5042225960282536}, {"country_id": "IN", "probability": 0.48348779264048036}, {"country_id": "NL", "probability": 0.007643852731150346}]}
{"name": "ritha", "country": [{"country_id": "ID", "probability": 1}]}
{"name": "rithiele", "country": []}
{"name": "rithvik", "country": []}
{"name": "riti", "country": []}
{"name": "ritik", "country": [{"country_id": "IN", "probability": 1}]}
{"name": "ritika", "country": [{"country_id": "IN", "probability": 1}]}
{"name": "rito", "country": [{"country_id": "ES", "probability": 0.4015784300946839}, {"country_id": "IT", "probability": 0.34445166564868684}, {"country_id": "FR", "probability": 0.2539699042566293}]}
{"name": "ritsuko", "country": [{"country_id": "JP", "probability": 1}]}
{"name": "ritsuro", "country": []}
{"name": "ritta", "country": [{"country_id": "TN", "probability": 0.556607794360866}, {"country_id": "MA", "probability": 0.23577307906833145}, {"country_id": "PT", "probability": 0.15038178634562682}]}
{"name": "rittick", "country": []}
{"name": "rittika", "country": []}
{"name": "rittipol", "country": []}
{"name": "rittwik", "country": []}
{"name": "ritu", "country": [{"country_id": "IN", "probability": 0.8078237313873102}, {"country_id": "FI", "probability": 0.1921762686126897}]}
{"name": "rituparna", "country": []}
{"name": "rituraj", "country": [{"country_id": "IN", "probability": 1}]}
{"name": "ritva", "country": [{"country_id": "FI", "probability": 0.9304585593334178}, {"country_id": "SE", "probability": 0.05440021161264772}, {"country_id": "", "probability": 0.015141229053934386}]}
{"name": "ritvik", "country": []}
{"name": "ritwik", "country": [{"country_id": "IN", "probability": 1}]}
{"name": "riui", "country": []}
{"name": "riva", "country": [{"country_id": "TN", "probability": 0.4404527630078619}, {"country_id": "ID", "probability": 0.3636917772012309}, {"country_id": "PH", "probability": 0.13692637547526712}]}
{"name": "rivaldo", "country": [{"country_id": "FR", "probability": 1}]}
{"name": "rivanda", "country": []}
{"name": "rivarol", "country": []}
{"name": "rivas", "country": [{"country_id": "ES", "probability": 1}]}
{"name": "rivayani", "country": []}
{"name": "riveiro", "country": []}
{"name": "rivera", "country": [{"country_id": "PH", "probability": 0.7777193188698824}, {"country_id": "ES", "probability": 0.15261330971896295}, {"country_id": "FR", "probability": 0.06966737141115473}]}
{"name": "rivero", "country": [{"country_id": "ES", "probability": 1}]}
{"name": "riveros", "country": []}
{"name": "rivers", "country": []}
{"name": "rivka", "country": [{"country_id": "IL", "probability": 1}]}
{"name": "rivki", "country": []}
{"name": "rivoltella", "country": []}
{"name": "riwens", "country": []}
{"name": "rixian", "country": []}
{"name": "riya", "country": [{"country_id": "IN", "probability": 0.889293876453068}, {"country_id": "ID", "probability": 0.08282408660218891}, {"country_id": "GB", "probability": 0.027882036944743085}]}
{"name": "riyad", "country": [{"country_id": "JO", "probability": 0.36826897016426535}, {"country_id": "DZ", "probability": 0.187626138064537}, {"country_id": "AZ", "probability": 0.18623192483181358}]}
{"name": "riyadi", "country": [{"country_id": "ID", "probability": 1}]}
{"name": "riyanti", "country": [{"country_id": "ID", "probability": 1}]}
{"name": "riyanto", "country": [{"country_id": "ID", "probability": 1}]}
{"name": "riyazahamad", "country": []}
{"name": "riyodina", "country": []}
{"name": "riyu", "country": []}
{"name": "riza", "country": [{"country_id": "PH", "probability": 0.40398464836549325}, {"country_id": "ID", "probability": 0.2978078595447344}, {"country_id": "AL", "probability": 0.11075872930876285}]}
{"name": "rizal", "country": [{"country_id": "ID", "probability": 0.6653665346797212}, {"country_id": "MY", "probability": 0.21203026156506194}, {"country_id": "SG", "probability": 0.1036742030215442}]}
{"name": "rizaldi", "country": [{"country_id": "ID", "probability": 1}]}
{"name": "rizen", "country": []}
{"name": "rizik", "country": []}
{"name": "rizka", "country": [{"country_id": "ID", "probability": 1}]}
{"name": "rizki", "country": [{"country_id": "ID", "probability": 0.9837472435866391}, {"country_id": "MA", "probability": 0.016252756413361026}]}
{"name": "rizky", "country": [{"country_id": "ID", "probability": 1.0000000000000002}]}
{"name": "rizmovich", "country": []}
{"name": "rizwan", "country": [{"country_id": "PK", "probability": 0.7997119215770319}, {"country_id": "AE", "probability": 0.0677178612398623}, {"country_id": "IN", "probability": 0.06702700756815455}]}
{"name": "rizwana", "country": [{"country_id": "PK", "probability": 0.9234306604143677}, {"country_id": "GB", "probability": 0.07656933958563221}]}
{"name": "rizwangul", "country": []}
{"name": "rizza", "country": [{"country_id": "PH", "probability": 0.9958017504971788}, {"country_id": "IT", "probability": 0.004198249502821152}]}
{"name": "rjw", "country": []}
{"name": "rmlan", "country": []}
{"name": "rmn", "country": []}
{"name": "rmw", "country": []}
{"name": "rna", "country": [{"country_id": "IL", "probability": 1}]}
{"name": "rnt", "country": []}
{"name": "ro", "country": [{"country_id": "SA", "probability": 0.3269852164118263}, {"country_id": "AR", "probability": 0.1323490199386586}, {"country_id": "NL", "probability": 0.10885365176550066}]}
{"name": "roa", "country": [{"country_id": "PH", "probability": 0.4751596018307741}, {"country_id": "MA", "probability": 0.42497936917460044}, {"country_id": "ES", "probability": 0.09986102899462544}]}
{"name": "roaa", "country": [{"country_id": "EG", "probability": 0.6064094790314362}, {"country_id": "SA", "probability": 0.3935905209685638}]}
{"name": "roald", "country": [{"country_id": "NO", "probability": 0.8300486600671606}, {"country_id": "NL", "probability": 0.16995133993283962}]}
{"name": "roanna", "country": []}
{"name": "roanny", "country": []}
{"name": "rob", "country": [{"country_id": "NL", "probability": 0.23683915611817938}, {"country_id": "CA", "probability": 0.15812073538965926}, {"country_id": "GB", "probability": 0.13581670671871307}]}
{"name": "roba", "country": [{"country_id": "KE", "probability": 0.46704137452938244}, {"country_id": "EG", "probability": 0.23187291797965584}, {"country_id": "SA", "probability": 0.16670468929535773}]}
{"name": "robab", "country": []}
{"name": "robb", "country": [{"country_id": "US", "probability": 0.5773365450868603}, {"country_id": "GB", "probability": 0.28060805853555615}, {"country_id": "IT", "probability": 0.09887928055481296}]}
{"name": "robbe", "country": [{"country_id": "BE", "probability": 0.9110695458568255}, {"country_id": "DE", "probability": 0.05665784587170068}, {"country_id": "IT", "probability": 0.032272608271473734}]}
{"name": "robbert", "country": [{"country_id": "NL", "probability": 0.9567363185088291}, {"country_id": "BE", "probability": 0.04326368149117082}]}
{"name": "robbie", "country": [{"country_id": "IE", "probability": 0.25287716405935595}, {"country_id": "AU", "probability": 0.14629667856412915}, {"country_id": "NL", "probability": 0.13904764517583376}]}
{"name": "robbin", "country": [{"country_id": "NL", "probability": 0.5762335500490003}, {"country_id": "SE", "probability": 0.31971737760974395}, {"country_id": "US", "probability": 0.08339637681984623}]}
{"name": "robby", "country": [{"country_id": "ID", "probability": 0.33117601776948996}, {"country_id": "BE", "probability": 0.17849483553728318}, {"country_id": "NL", "probability": 0.09346113189486065}]}
{"name": "roberio", "country": []}
{"name": "robert", "country": [{"country_id": "US", "probability": 0.09094421290695878}, {"country_id": "CA", "probability": 0.05087886862092505}, {"country_id": "AU", "probability": 0.04267673002984972}]}
{"name": "roberta", "country": [{"country_id": "IT", "probability": 0.3112853168619523}, {"country_id": "MT", "probability": 0.15099738057549916}, {"country_id": "LT", "probability": 0.10243528418138605}]}
{"name": "robertas", "country": [{"country_id": "LT", "probability": 0.9915243967679086}, {"country_id": "GB", "probability": 0.008475603232091377}]}
{"name": "robertina", "country": [{"country_id": "IT", "probability": 1}]}
{"name": "robertjan", "country": [{"country_id": "NL", "probability": 0.9999999999999999}]}
{"name": "robertjay", "country": []}
{"name": "roberto", "country": [{"country_id": "SV", "probability": 0.07764674963291662}, {"country_id": "IT", "probability": 0.05777894235550739}, {"country_id": "SM", "probability": 0.05167716381253571}]}
{"name": "roberton", "country": []}
{"name": "robertpaul", "country": []}
{"name": "roberts", "country": [{"country_id": "LV", "probability": 0.9647312091503575}, {"country_id": "NG", "probability": 0.022771193182462422}, {"country_id": "GB", "probability": 0.009377179602852975}]}
{"name": "robertson", "country": [{"country_id": "PH", "probability": 1}]}
{"name": "robertus", "country": [{"country_id": "ID", "probability": 1}]}
{"name": "robest", "country": []}
{"name": "robet", "country": []}
{"name": "robin", "country": [{"country_id": "SE", "probability": 0.18696558028344626}, {"country_id": "NL", "probability": 0.08844133766073935}, {"country_id": "NP", "probability": 0.056474074152228874}]}
{"name": "robina", "country": [{"country_id": "PH", "probability": 0.46334830875491745}, {"country_id": "NL", "probability": 0.2747844398666875}, {"country_id": "GB", "probability": 0.15016042153939335}]}
{"name": "robinson", "country": [{"country_id": "CO", "probability": 0.22400711633896234}, {"country_id": "DO", "probability": 0.21678066810953378}, {"country_id": "CL", "probability": 0.14780749592319814}]}
{"name": "robiul", "country": []}
{"name": "robleskelly", "country": []}
{"name": "robrecht", "country": [{"country_id": "BE", "probability": 1}]}
{"name": "robson", "country": [{"country_id": "BR", "probability": 0.7795539199047848}, {"country_id": "JP", "probability": 0.10023915076294226}, {"country_id": "AO", "probability": 0.045257635241145795}]}
{"name": "robu", "country": [{"country_id": "RO", "probability": 0.9767779081124925}, {"country_id": "IT", "probability": 0.023222091887507457}]}
{"name": "roby", "country": [{"country_id": "IT", "probability": 0.37476121349056235}, {"country_id": "LU", "probability": 0.12219936133840235}, {"country_id": "CH", "probability": 0.0823622142784919}]}
{"name": "robyn", "country": [{"country_id": "AU", "probability": 0.3359219796226494}, {"country_id": "ZA", "probability": 0.2225838361589319}, {"country_id": "CA", "probability": 0.12883190145309376}]}
{"name": "robyne", "country": []}
{"name": "roc", "country": [{"country_id": "CN", "probability": 0.6960001474211794}, {"country_id": "ES", "probability": 0.16988441421965036}, {"country_id": "FR", "probability": 0.07717326190433711}]}
{"name": "rocael", "country": []}
{"name": "rocci", "country": []}
{"name": "rocco", "country": [{"country_id": "IT", "probability": 0.41883257281717173}, {"country_id": "CH", "probability": 0.11265191424381667}, {"country_id": "", "probability": 0.07525704420422347}]}
{"name": "roch", "country": [{"country_id": "CA", "probability": 0.37309197365476443}, {"country_id": "CI", "probability": 0.2927151507332521}, {"country_id": "MA", "probability": 0.145203145082433}]}
{"name": "rochard", "country": []}
{"name": "rochdi", "country": [{"country_id": "TN", "probability": 0.49975737507925727}, {"country_id": "MA", "probability": 0.3013668733643849}, {"country_id": "DZ", "probability": 0.16727753806834111}]}
{"name": "rochel", "country": [{"country_id": "PH", "probability": 1}]}
{"name": "rochell", "country": [{"country_id": "PH", "probability": 0.9999999999999999}]}
{"name": "rochelle", "country": [{"country_id": "PH", "probability": 0.6263099517318306}, {"country_id": "ZA", "probability": 0.19981593584305266}, {"country_id": "SG", "probability": 0.06125859702651043}]}
{"name": "rochester", "country": []}
{"name": "rochhugo", "country": []}
{"name": "rochman", "country": [{"country_id": "ID", "probability": 0.9999999999999999}]}
{"name": "rochon", "country": []}
{"name": "rocio", "country": [{"country_id": "ES", "probability": 0.2618333813756449}, {"country_id": "PE", "probability": 0.166609054283174}, {"country_id": "AR", "probability": 0.13899386299033312}]}
{"name": "rock", "country": [{"country_id": "BJ", "probability": 0.16626639936759155}, {"country_id": "OM", "probability": 0.10488902887598484}, {"country_id": "TW", "probability": 0.10277219130436906}]}
{"name": "rocky", "country": [{"country_id": "IN", "probability": 0.14214246115341048}, {"country_id": "HK", "probability": 0.07837843174339947}, {"country_id": "QA", "probability": 0.057331698874483375}]}
{"name": "rocsana", "country": [{"country_id": "RO", "probability": 1}]}
{"name": "rod", "country": [{"country_id": "CA", "probability": 0.22376403761747682}, {"country_id": "AU", "probability": 0.21357096610354226}, {"country_id": "US", "probability": 0.09741534581557765}]}
{"name": "roda", "country": [{"country_id": "DJ", "probability": 0.8852526128864089}, {"country_id": "PH", "probability": 0.11264125272512074}, {"country_id": "FR", "probability": 0.0021061343884701622}]}
{"name": "rodal", "country": []}
{"name": "rodas", "country": [{"country_id": "PT", "probability": 1}]}
{"name": "rodd", "country": []}
{"name": "roddran", "country": []}
{"name": "roddy", "country": [{"country_id": "CD", "probability": 0.7026814161566837}, {"country_id": "CM", "probability": 0.18675979622435385}, {"country_id": "GB", "probability": 0.08068806501357949}]}
{"name": "roded", "country": []}
{"name": "rodel", "country": [{"country_id": "PH", "probability": 0.9649604109513465}, {"country_id": "SA", "probability": 0.035039589048653466}]}
{"name": "roderic", "country": [{"country_id": "PH", "probability": 1}]}
{"name": "roderich", "country": [{"country_id": "DE", "probability": 1}]}
{"name": "roderick", "country": [{"country_id": "MT", "probability": 0.48458551196044924}, {"country_id": "PH", "probability": 0.2825403619422767}, {"country_id": "CA", "probability": 0.054840383556559076}]}
{"name": "roderik", "country": [{"country_id": "NL", "probability": 1}]}
{"name": "rodger", "country": [{"country_id": "ZA", "probability": 0.3970862598637147}, {"country_id": "US", "probability": 0.26365651464421985}, {"country_id": "GB", "probability": 0.160291232432654}]}
{"name": "rodica", "country": [{"country_id": "MD", "probability": 0.6775146447639926}, {"country_id": "RO", "probability": 0.2839204723435181}, {"country_id": "", "probability": 0.019889021914151133}]}
{"name": "rodie", "country": []}
{"name": "rodilina", "country": []}
{"name": "rodion", "country": [{"country_id": "UA", "probability": 0.5280937650872991}, {"country_id": "RU", "probability": 0.4315323423655037}, {"country_id": "DE", "probability": 0.040373892547197095}]}
{"name": "rodionov", "country": []}
{"name": "rodlescia", "country": []}
{"name": "rodmonga", "country": []}
{"name": "rodney", "country": [{"country_id": "AU", "probability": 0.29011588762499824}, {"country_id": "US", "probability": 0.17936074160300822}, {"country_id": "ZW", "probability": 0.16841148825561916}]}
{"name": "rodolf", "country": [{"country_id": "PH", "probability": 0.7826500152801366}, {"country_id": "FR", "probability": 0.21734998471986347}]}
{"name": "rodolfo", "country": [{"country_id": "CR", "probability": 0.16206346545158623}, {"country_id": "UY", "probability": 0.10218069125821506}, {"country_id": "MX", "probability": 0.09743068569812177}]}
{"name": "rodolphe", "country": [{"country_id": "BJ", "probability": 0.2767854098030746}, {"country_id": "TG", "probability": 0.18042312116107095}, {"country_id": "CI", "probability": 0.14717554544805314}]}
{"name": "rodolpho", "country": [{"country_id": "BR", "probability": 1}]}
{"name": "rodoula", "country": [{"country_id": "GR", "probability": 1}]}
{"name": "rodreck", "country": []}
{"name": "rodri", "country": [{"country_id": "AR", "probability": 0.6014798845941367}, {"country_id": "ES", "probability": 0.33453111879194586}, {"country_id": "PT", "probability": 0.05801018806654151}]}
{"name": "rodric", "country": []}
{"name": "rodrick", "country": [{"country_id": "CD", "probability": 0.9477068985413427}, {"country_id": "US", "probability": 0.05229310145865723}]}
{"name": "rodrigo", "country": [{"country_id": "CL", "probability": 0.18003444384345968}, {"country_id": "BR", "probability": 0.15842998950044426}, {"country_id": "PY", "probability": 0.10319727631989847}]}
{"name": "rodrigue", "country": [{"country_id": "BJ", "probability": 0.20699402043252005}, {"country_id": "GA", "probability": 0.15865595812391725}, {"country_id": "TG", "probability": 0.15507193952117132}]}
{"name": "rodrigues", "country": [{"country_id": "LU", "probability": 0.29079550144449007}, {"country_id": "MZ", "probability": 0.26166822336911677}, {"country_id": "AO", "probability": 0.210605535868531}]}
{"name": "rodriguez", "country": [{"country_id": "CD", "probability": 0.4054573634379936}, {"country_id": "CM", "probability": 0.32640248577442976}, {"country_id": "CH", "probability": 0.07027055568759341}]}
{"name": "rodrygo", "country": []}
{"name": "rodziah", "country": []}
{"name": "roediger", "country": []}
{"name": "roee", "country": [{"country_id": "IL", "probability": 1}]}
{"name": "roei", "country": [{"country_id": "IL", "probability": 1}]}
{"name": "roel", "country": [{"country_id": "NL", "probability": 0.558056531711792}, {"country_id": "PH", "probability": 0.30224187695611787}, {"country_id": "BE", "probability": 0.128228908173626}]}
{"name": "roeland", "country": [{"country_id": "NL", "probability": 0.6398846711198639}, {"country_id": "BE", "probability": 0.36011532888013614}]}
{"name": "roelien", "country": [{"country_id": "ZA", "probability": 0.6080942313438963}, {"country_id": "NL", "probability": 0.3919057686561036}]}
{"name": "roelof", "country": [{"country_id": "NL", "probability": 0.7533385342991887}, {"country_id": "ZA", "probability": 0.2466614657008112}]}
{"name": "roemer", "country": []}
{"name": "roesnita", "country": []}
{"name": "rofiqoh", "country": []}
{"name": "rofizah", "country": []}
{"name": "rogelio", "country": [{"country_id": "MX", "probability": 0.39425088482574916}, {"country_id": "PH", "probability": 0.35022779287805206}, {"country_id": "CL", "probability": 0.07421381522746663}]}
{"name": "roger", "country": [{"country_id": "CD", "probability": 0.06472016060539466}, {"country_id": "NO", "probability": 0.050673391417776416}, {"country_id": "NI", "probability": 0.049945177967560185}]}
{"name": "rogeria", "country": []}
{"name": "rogerio", "country": [{"country_id": "BR", "probability": 0.42583743778318167}, {"country_id": "MZ", "probability": 0.2576849215476148}, {"country_id": "PT", "probability": 0.12600208097298443}]}
{"name": "rogers", "country": [{"country_id": "UG", "probability": 0.6248374931657875}, {"country_id": "TZ", "probability": 0.23764757137785175}, {"country_id": "KE", "probability": 0.12061314860327417}]}
{"name": "rogert", "country": []}
{"name": "roghayeh", "country": []}
{"name": "rogier", "country": [{"country_id": "NL", "probability": 0.9528602219583808}, {"country_id": "BE", "probability": 0.047139778041619194}]}
{"name": "rognvaldur", "country": []}
{"name": "roh", "country": [{"country_id": "KR", "probability": 0.6420296415579568}, {"country_id": "SA", "probability": 0.3331877662495297}, {"country_id": "FR", "probability": 0.024782592192513504}]}
{"name": "rohail", "country": [{"country_id": "PK", "probability": 0.9824582664031344}, {"country_id": "GB", "probability": 0.01754173359686557}]}
{"name": "rohaiza", "country": [{"country_id": "MY", "probability": 0.9999999999999999}]}
{"name": "rohaizah", "country": []}
{"name": "rohaizan", "country": []}
{"name": "rohallah", "country": []}
{"name": "rohan", "country": [{"country_id": "LK", "probability": 0.45356742181161486}, {"country_id": "IN", "probability": 0.2896327742493346}, {"country_id": "MU", "probability": 0.131012257972531}]}
{"name": "rohana", "country": [{"country_id": "LK", "probability": 0.7530959412977325}, {"country_id": "MY", "probability": 0.17620396540168953}, {"country_id": "SG", "probability": 0.07070009330057808}]}
{"name": "rohani", "country": [{"country_id": "MY", "probability": 0.8093447142741296}, {"country_id": "ID", "probability": 0.19065528572587034}]}
{"name": "rohany", "country": []}
{"name": "rohayah", "country": []}
{"name": "rohayu", "country": [{"country_id": "MY", "probability": 1}]}
{"name": "roheet", "country": []}
{"name": "rohhss", "country": []}
{"name": "rohini", "country": [{"country_id": "IN", "probability": 1}]}
{"name": "rohit", "country": [{"country_id": "IN", "probability": 0.6774313754275993}, {"country_id": "NP", "probability": 0.28455775145736256}, {"country_id": "SG", "probability": 0.01898241045908725}]}
{"name": "rohith", "country": [{"country_id": "IN", "probability": 0.9999999999999999}]}
{"name": "rohiza", "country": []}
{"name": "rohizah", "country": []}
{"name": "rohmad", "country": [{"country_id": "ID", "probability": 1}]}
{"name": "rohmah", "country": []}
{"name": "rohollah", "country": [{"country_id": "IR", "probability": 1}]}
{"name": "roi", "country": [{"country_id": "IL", "probability": 0.5530492957385023}, {"country_id": "TN", "probability": 0.18803413936808105}, {"country_id": "PH", "probability": 0.04849631438453819}]}
{"name": "roichi", "country": []}
{"name": "roine", "country": [{"country_id": "SE", "probability": 1}]}
{"name": "roisin", "country": [{"country_id": "IE", "probability": 0.9335267867198691}, {"country_id": "GB", "probability": 0.06647321328013076}]}
{"name": "roja", "country": [{"country_id": "IR", "probability": 0.9721254672953605}, {"country_id": "DE", "probability": 0.02787453270463931}]}
{"name": "rojas", "country": [{"country_id": "ES", "probability": 0.6795490245359396}, {"country_id": "FR", "probability": 0.32045097546406043}]}
{"name": "rojiemiahd", "country": []}
{"name": "rojin", "country": [{"country_id": "IR", "probability": 0.6678381053514095}, {"country_id": "TR", "probability": 0.1665436223614487}, {"country_id": "DE", "probability": 0.10900460299163454}]}
{"name": "rojukurthi", "country": []}
{"name": "rok", "country": [{"country_id": "SI", "probability": 0.9817640257042765}, {"country_id": "KR", "probability": 0.008561905021265059}, {"country_id": "", "probability": 0.007911322274754558}]}
{"name": "rokas", "country": [{"country_id": "LT", "probability": 0.9933517219777958}, {"country_id": "GB", "probability": 0.006648278022204316}]}
{"name": "rokhaya", "country": [{"country_id": "SN", "probability": 0.9979001170084305}, {"country_id": "FR", "probability": 0.002099882991569528}]}
{"name": "rokhima", "country": []}
{"name": "rokia", "country": [{"country_id": "ML", "probability": 0.6942760038878093}, {"country_id": "CI", "probability": 0.25436811184406355}, {"country_id": "MA", "probability": 0.031620903669659715}]}
{"name": "rokiah", "country": [{"country_id": "MY", "probability": 1}]}
{"name": "roksana", "country": [{"country_id": "PL", "probability": 0.7657625217138424}, {"country_id": "IE", "probability": 0.09052495486587046}, {"country_id": "", "probability": 0.06420664002639878}]}
{"name": "rola", "country": [{"country_id": "LB", "probability": 0.5299291271418948}, {"country_id": "JO", "probability": 0.23427295706065882}, {"country_id": "IL", "probability": 0.10496839060334186}]}
{"name": "rolan", "country": [{"country_id": "PH", "probability": 0.8038640328002877}, {"country_id": "ID", "probability": 0.14247016244607985}, {"country_id": "ES", "probability": 0.032933448951658006}]}
{"name": "roland", "country": [{"country_id": "HU", "probability": 0.10181855295140695}, {"country_id": "AT", "probability": 0.06800349432863208}, {"country_id": "CG", "probability": 0.06747161890391544}]}
{"name": "rolando", "country": [{"country_id": "BO", "probability": 0.1781912182935927}, {"country_id": "CR", "probability": 0.171799226650202}, {"country_id": "PA", "probability": 0.11974599632996283}]}
{"name": "rolandth", "country": []}
{"name": "roldan", "country": [{"country_id": "PH", "probability": 0.983132859812786}, {"country_id": "ES", "probability": 0.011599720578506036}, {"country_id": "FR", "probability": 0.00526741960870798}]}
{"name": "rolf", "country": [{"country_id": "NO", "probability": 0.35120868160849383}, {"country_id": "CH", "probability": 0.19168189378632533}, {"country_id": "SE", "probability": 0.15867609745127034}]}
{"name": "rolfy", "country": []}
{"name": "rolheiser", "country": []}
{"name": "roli", "country": [{"country_id": "HU", "probability": 0.34407038247726135}, {"country_id": "CH", "probability": 0.3344088033247646}, {"country_id": "AT", "probability": 0.24054994758449819}]}
{"name": "roliana", "country": []}
