{"name": "paladines", "country": []}
{"name": "palaiahnakote", "country": []}
{"name": "palaiologos", "country": []}
{"name": "palaiyah", "country": []}
{"name": "palak", "country": [{"country_id": "IN", "probability": 0.9999999999999999}]}
{"name": "palakorn", "country": []}
{"name": "palanisamy", "country": [{"country_id": "IN", "probability": 1}]}
{"name": "palanivel", "country": []}
{"name": "palash", "country": [{"country_id": "BD", "probability": 0.9087195780998233}, {"country_id": "IN", "probability": 0.09128042190017659}]}
{"name": "palashi", "country": []}
{"name": "palayil", "country": []}
{"name": "palfi", "country": [{"country_id": "RO", "probability": 1.0000000000000002}]}
{"name": "palghat", "country": []}
{"name": "palgrave", "country": []}
{"name": "pali", "country": [{"country_id": "SK", "probability": 0.5525814917859994}, {"country_id": "HU", "probability": 0.3451654917693518}, {"country_id": "AR", "probability": 0.057213967053334355}]}
{"name": "palie", "country": []}
{"name": "palitha", "country": []}
{"name": "pallab", "country": [{"country_id": "IN", "probability": 1}]}
{"name": "pallabi", "country": []}
{"name": "pallam", "country": []}
{"name": "pallapa", "country": []}
{"name": "pallav", "country": [{"country_id": "IN", "probability": 1}]}
{"name": "pallavi", "country": [{"country_id": "IN", "probability": 1}]}
{"name": "pallaw", "country": []}
{"name": "palle", "country": [{"country_id": "DK", "probability": 0.8550293817081075}, {"country_id": "SE", "probability": 0.1198450080686709}, {"country_id": "", "probability": 0.0207351223013014}]}
{"name": "pallis", "country": []}
{"name": "pallop", "country": []}
{"name": "palma", "country": [{"country_id": "IT", "probability": 0.37550932211489213}, {"country_id": "", "probability": 0.24832448680808794}, {"country_id": "PT", "probability": 0.16730533264191005}]}
{"name": "palmert", "country": []}
{"name": "palmieri", "country": [{"country_id": "IT", "probability": 1}]}
{"name": "palmira", "country": [{"country_id": "MZ", "probability": 0.4029520361862518}, {"country_id": "AO", "probability": 0.3803841339448492}, {"country_id": "PT", "probability": 0.14327379969739323}]}
{"name": "palmyre", "country": [{"country_id": "FR", "probability": 1}]}
{"name": "paloma", "country": [{"country_id": "ES", "probability": 0.22050991512256374}, {"country_id": "CL", "probability": 0.2018933732885281}, {"country_id": "MX", "probability": 0.11584225671622075}]}
{"name": "palomaki", "country": []}
{"name": "palomino", "country": [{"country_id": "ES", "probability": 0.9999999999999999}]}
{"name": "palonen", "country": []}
{"name": "palupi", "country": [{"country_id": "ID", "probability": 1}]}
{"name": "paluri", "country": []}
{"name": "palvadi", "country": []}
{"name": "pam", "country": [{"country_id": "GB", "probability": 0.11889895304102575}, {"country_id": "TH", "probability": 0.10012770564569091}, {"country_id": "ZA", "probability": 0.09979941050573872}]}
{"name": "pamala", "country": []}
{"name": "pamara", "country": []}
{"name": "pamela", "country": [{"country_id": "CL", "probability": 0.078437705939072}, {"country_id": "BO", "probability": 0.070157785875441}, {"country_id": "GM", "probability": 0.06544970954242281}]}
{"name": "pameljit", "country": []}
{"name": "pamidi", "country": []}
{"name": "pamidimukkalaanupya", "country": []}
{"name": "pamina", "country": []}
{"name": "pamm", "country": []}
{"name": "pammi", "country": []}
{"name": "pan", "country": [{"country_id": "MM", "probability": 0.2463504154951806}, {"country_id": "TW", "probability": 0.12937367871969463}, {"country_id": "TH", "probability": 0.106017067290849}]}
{"name": "panagiota", "country": [{"country_id": "GR", "probability": 0.5658106780675408}, {"country_id": "CY", "probability": 0.4060153014536699}, {"country_id": "", "probability": 0.018979703243325038}]}
{"name": "panagiotis", "country": [{"country_id": "GR", "probability": 0.640474494741234}, {"country_id": "CY", "probability": 0.3428711034000812}, {"country_id": "", "probability": 0.010483328224433673}]}
{"name": "panagote", "country": []}
{"name": "panatda", "country": [{"country_id": "TH", "probability": 1}]}
{"name": "panayiota", "country": [{"country_id": "CY", "probability": 1}]}
{"name": "panayiotis", "country": [{"country_id": "CY", "probability": 0.9439845042499664}, {"country_id": "GR", "probability": 0.053667588148290556}, {"country_id": "GB", "probability": 0.0023479076017430293}]}
{"name": "panayotes", "country": []}
{"name": "panayotis", "country": [{"country_id": "GR", "probability": 1}]}
{"name": "panchal", "country": []}
{"name": "panchit", "country": []}
{"name": "panda", "country": [{"country_id": "HK", "probability": 0.34350820326062087}, {"country_id": "CN", "probability": 0.2045435235983478}, {"country_id": "TH", "probability": 0.11685575781518802}]}
{"name": "pande", "country": [{"country_id": "ID", "probability": 1}]}
{"name": "pandharinath", "country": []}
{"name": "pandian", "country": [{"country_id": "IN", "probability": 1}]}
{"name": "pando", "country": [{"country_id": "IT", "probability": 1}]}
{"name": "pandore", "country": [{"country_id": "FR", "probability": 1.0000000000000002}]}
{"name": "pandu", "country": [{"country_id": "ID", "probability": 0.8634330316751269}, {"country_id": "IN", "probability": 0.13656696832487322}]}
{"name": "pandula", "country": []}
{"name": "panduranga", "country": []}
{"name": "panfeng", "country": []}
{"name": "pang", "country": [{"country_id": "TH", "probability": 0.296516892255365}, {"country_id": "HK", "probability": 0.2716904090628977}, {"country_id": "SG", "probability": 0.20546606332390838}]}
{"name": "pangan", "country": []}
{"name": "pangfeng", "country": []}
{"name": "pangiotis", "country": []}
{"name": "pangning", "country": []}
{"name": "pangyen", "country": []}
{"name": "pangyu", "country": []}
{"name": "pani", "country": [{"country_id": "IR", "probability": 0.8452468765536837}, {"country_id": "PL", "probability": 0.12117191719708055}, {"country_id": "ES", "probability": 0.033581206249235905}]}
{"name": "paniccia", "country": []}
{"name": "panicos", "country": [{"country_id": "CY", "probability": 1}]}
{"name": "panida", "country": [{"country_id": "TH", "probability": 1}]}
{"name": "panigrahy", "country": []}
{"name": "panigyrakis", "country": []}
{"name": "panindra", "country": []}
{"name": "panjai", "country": []}
{"name": "panjun", "country": []}
{"name": "pankaj", "country": [{"country_id": "IN", "probability": 0.957713078295587}, {"country_id": "SG", "probability": 0.026366486238851093}, {"country_id": "GB", "probability": 0.00588713094812909}]}
{"name": "pankajeshwara", "country": []}
{"name": "pankajkumar", "country": []}
{"name": "pankhari", "country": []}
{"name": "pankhuri", "country": []}
{"name": "pankoo", "country": []}
{"name": "pankti", "country": []}
{"name": "pankush", "country": []}
{"name": "panlong", "country": []}
{"name": "pannagadatta", "country": []}
{"name": "pannee", "country": [{"country_id": "TH", "probability": 1}]}
{"name": "panni", "country": [{"country_id": "HU", "probability": 1}]}
{"name": "pano", "country": [{"country_id": "GR", "probability": 0.8433135456791591}, {"country_id": "DE", "probability": 0.1566864543208409}]}
{"name": "panom", "country": [{"country_id": "TH", "probability": 1}]}
{"name": "panopoulos", "country": []}
{"name": "panorea", "country": []}
{"name": "panos", "country": [{"country_id": "GR", "probability": 0.8023967967947353}, {"country_id": "CY", "probability": 0.18423803837189737}, {"country_id": "", "probability": 0.007707633049545569}]}
{"name": "panote", "country": []}
{"name": "panova", "country": []}
{"name": "panpan", "country": [{"country_id": "CN", "probability": 0.5990560661965346}, {"country_id": "TH", "probability": 0.2933493050742448}, {"country_id": "FR", "probability": 0.10759462872922064}]}
{"name": "panraphee", "country": []}
{"name": "pansak", "country": []}
{"name": "pansoo", "country": []}
{"name": "panstwowe", "country": []}
{"name": "pansy", "country": []}
{"name": "pantakan", "country": []}
{"name": "pantea", "country": [{"country_id": "IR", "probability": 0.8175049564341407}, {"country_id": "RO", "probability": 0.18249504356585924}]}
{"name": "panteleimon", "country": []}
{"name": "pantelic", "country": []}
{"name": "pantelimon", "country": [{"country_id": "RO", "probability": 1.0000000000000002}]}
{"name": "pantelimongeorge", "country": []}
{"name": "pantelis", "country": [{"country_id": "CY", "probability": 0.502993517791748}, {"country_id": "GR", "probability": 0.48859983999675044}, {"country_id": "", "probability": 0.006131527151857754}]}
{"name": "pantelos", "country": [{"country_id": "GR", "probability": 1}]}
{"name": "panthratan", "country": []}
{"name": "pantipa", "country": [{"country_id": "TH", "probability": 1}]}
{"name": "pantoja", "country": []}
{"name": "pantung", "country": []}
{"name": "panu", "country": [{"country_id": "FI", "probability": 0.7842315249398282}, {"country_id": "TH", "probability": 0.21576847506017172}]}
{"name": "panwipha", "country": []}
{"name": "panya", "country": [{"country_id": "TH", "probability": 1}]}
{"name": "panzarasa", "country": []}
{"name": "panzu", "country": []}
{"name": "pao", "country": [{"country_id": "EC", "probability": 0.27346677000820346}, {"country_id": "CO", "probability": 0.18770330541537714}, {"country_id": "AR", "probability": 0.1772330395533476}]}
{"name": "paochuan", "country": []}
{"name": "paochung", "country": []}
{"name": "paojangul", "country": []}
{"name": "paoju", "country": []}
{"name": "paojyh", "country": []}
{"name": "paola", "country": [{"country_id": "CO", "probability": 0.13487865037732524}, {"country_id": "BO", "probability": 0.12152134329927282}, {"country_id": "EC", "probability": 0.07953354859314632}]}
{"name": "paolien", "country": []}
{"name": "paoling", "country": []}
{"name": "paolo", "country": [{"country_id": "IT", "probability": 0.32633101535598286}, {"country_id": "SM", "probability": 0.28303247098009965}, {"country_id": "", "probability": 0.05346270096699698}]}
{"name": "paonan", "country": []}
{"name": "paora", "country": []}
{"name": "paota", "country": []}
{"name": "paoyang", "country": []}
{"name": "paoyueh", "country": []}
{"name": "paoyung", "country": []}
{"name": "papa", "country": [{"country_id": "SN", "probability": 0.5513604809634277}, {"country_id": "MR", "probability": 0.17210701182816557}, {"country_id": "ML", "probability": 0.121237109250176}]}
{"name": "papadopoulos", "country": [{"country_id": "GR", "probability": 1}]}
{"name": "paparao", "country": []}
{"name": "papattaranan", "country": []}
{"name": "pape", "country": [{"country_id": "SN", "probability": 0.7818859076829114}, {"country_id": "MR", "probability": 0.16501020804878677}, {"country_id": "ML", "probability": 0.03357653541598546}]}
{"name": "papi", "country": [{"country_id": "SN", "probability": 0.455315536038214}, {"country_id": "ML", "probability": 0.18879695779332512}, {"country_id": "ZA", "probability": 0.0727802254657794}]}
{"name": "papin", "country": [{"country_id": "FR", "probability": 1.0000000000000002}]}
{"name": "papinya", "country": []}
{"name": "papir", "country": []}
{"name": "pappi", "country": []}
{"name": "pappu", "country": [{"country_id": "IN", "probability": 1}]}
{"name": "papri", "country": []}
{"name": "paquolacasey", "country": []}
{"name": "par", "country": [{"country_id": "SE", "probability": 0.408870092425911}, {"country_id": "IR", "probability": 0.245669856437579}, {"country_id": "TH", "probability": 0.1894210973945996}]}
{"name": "paradowska", "country": []}
{"name": "parag", "country": [{"country_id": "IN", "probability": 0.9834427499135103}, {"country_id": "GB", "probability": 0.016557250086489762}]}
{"name": "paraje", "country": []}
{"name": "param", "country": [{"country_id": "IN", "probability": 0.8127708732118184}, {"country_id": "MY", "probability": 0.18722912678818168}]}
{"name": "parama", "country": []}
{"name": "paramaporn", "country": []}
{"name": "paramasivam", "country": []}
{"name": "parames", "country": [{"country_id": "MY", "probability": 1}]}
{"name": "parameshwar", "country": []}
{"name": "parameshwaran", "country": []}
{"name": "parameswaran", "country": []}
{"name": "paramin", "country": []}
{"name": "paramita", "country": [{"country_id": "ID", "probability": 1}]}
{"name": "paramitha", "country": [{"country_id": "ID", "probability": 1}]}
{"name": "paramjeet", "country": [{"country_id": "IN", "probability": 1}]}
{"name": "paramjit", "country": [{"country_id": "IN", "probability": 1}]}
{"name": "paramveer", "country": []}
{"name": "paramvir", "country": []}
{"name": "parantapa", "country": []}
{"name": "paras", "country": [{"country_id": "IN", "probability": 0.9823192150349904}, {"country_id": "GB", "probability": 0.017680784965009737}]}
{"name": "paraschos", "country": []}
{"name": "paraskevas", "country": [{"country_id": "GR", "probability": 1}]}
{"name": "paraskevi", "country": [{"country_id": "GR", "probability": 1}]}
{"name": "parastoo", "country": [{"country_id": "IR", "probability": 1}]}
{"name": "parastou", "country": []}
{"name": "parcilene", "country": []}
{"name": "pard", "country": []}
{"name": "pardamean", "country": []}
{"name": "pardeep", "country": [{"country_id": "IN", "probability": 0.9629019451926459}, {"country_id": "GB", "probability": 0.03709805480735418}]}
{"name": "pardha", "country": []}
{"name": "pardis", "country": [{"country_id": "IR", "probability": 1}]}
{"name": "pardo", "country": [{"country_id": "ES", "probability": 0.5901178259916406}, {"country_id": "IT", "probability": 0.4098821740083593}]}
{"name": "pardoe", "country": []}
{"name": "pardon", "country": [{"country_id": "ZW", "probability": 0.9999999999999999}]}
{"name": "paredes", "country": []}
{"name": "parena", "country": []}
{"name": "parepally", "country": []}
{"name": "paresh", "country": [{"country_id": "IN", "probability": 0.9753483673208985}, {"country_id": "GB", "probability": 0.02465163267910167}]}
{"name": "paresha", "country": []}
{"name": "parham", "country": [{"country_id": "IR", "probability": 1}]}
{"name": "pari", "country": [{"country_id": "IR", "probability": 0.5588033580302452}, {"country_id": "PK", "probability": 0.2619019399899172}, {"country_id": "IN", "probability": 0.13154397646246488}]}
{"name": "paria", "country": [{"country_id": "IR", "probability": 1}]}
{"name": "parida", "country": []}
{"name": "paridhi", "country": []}
{"name": "parihar", "country": []}
{"name": "parijat", "country": []}
{"name": "parikh", "country": []}
{"name": "parikshit", "country": [{"country_id": "IN", "probability": 1}]}
{"name": "parilah", "country": []}
{"name": "parima", "country": []}
{"name": "parimal", "country": [{"country_id": "IN", "probability": 1}]}
{"name": "parimala", "country": [{"country_id": "MY", "probability": 1}]}
{"name": "parin", "country": [{"country_id": "TH", "probability": 1}]}
{"name": "parina", "country": []}
{"name": "parinda", "country": [{"country_id": "TH", "probability": 1}]}
{"name": "parinita", "country": []}
{"name": "parinya", "country": [{"country_id": "TH", "probability": 0.9999999999999999}]}
{"name": "parirokh", "country": []}
{"name": "paris", "country": [{"country_id": "CY", "probability": 0.42631794320059113}, {"country_id": "GR", "probability": 0.33858454664234783}, {"country_id": "IR", "probability": 0.029176492873452295}]}
{"name": "parisa", "country": [{"country_id": "IR", "probability": 0.9675391817368273}, {"country_id": "TH", "probability": 0.013806041573203386}, {"country_id": "SE", "probability": 0.012688244672989617}]}
{"name": "parissa", "country": [{"country_id": "IR", "probability": 1}]}
{"name": "paritosh", "country": [{"country_id": "IN", "probability": 1}]}
{"name": "parizad", "country": []}
{"name": "park", "country": [{"country_id": "KR", "probability": 0.8590216387778363}, {"country_id": "CN", "probability": 0.049243335421983586}, {"country_id": "JP", "probability": 0.02494043831835599}]}
{"name": "parker", "country": [{"country_id": "CM", "probability": 0.2867595929584523}, {"country_id": "CI", "probability": 0.19859592647745683}, {"country_id": "US", "probability": 0.19470141413198838}]}
{"name": "parkhideh", "country": []}
{"name": "parkjongchan", "country": []}
{"name": "parkjooseok", "country": []}
{"name": "parks", "country": []}
{"name": "parkseonghwan", "country": []}
{"name": "parkseungbong", "country": []}
{"name": "parksunmee", "country": []}
{"name": "parlo", "country": []}
{"name": "parmeet", "country": []}
{"name": "parminder", "country": [{"country_id": "IN", "probability": 0.9098629559471219}, {"country_id": "GB", "probability": 0.09013704405287798}]}
{"name": "parmit", "country": []}
{"name": "parmod", "country": [{"country_id": "IN", "probability": 1}]}
{"name": "parmutia", "country": []}
{"name": "parnell", "country": []}
{"name": "parnicky", "country": []}
{"name": "parnpan", "country": []}
{"name": "paromita", "country": []}
{"name": "parongama", "country": []}
{"name": "parosh", "country": []}
{"name": "parra", "country": [{"country_id": "ES", "probability": 0.6893671749206609}, {"country_id": "FR", "probability": 0.3106328250793392}]}
{"name": "parreiras", "country": []}
{"name": "parrenoselva", "country": []}
{"name": "parris", "country": []}
{"name": "parry", "country": [{"country_id": "IN", "probability": 1}]}
{"name": "partezani", "country": []}
{"name": "parth", "country": [{"country_id": "IN", "probability": 0.9871396791064626}, {"country_id": "GB", "probability": 0.01286032089353743}]}
{"name": "partha", "country": [{"country_id": "IN", "probability": 1}]}
{"name": "parthasarathi", "country": [{"country_id": "IN", "probability": 1}]}
{"name": "parthasarathy", "country": [{"country_id": "IN", "probability": 1}]}
{"name": "partheeban", "country": []}
{"name": "parthiban", "country": [{"country_id": "IN", "probability": 0.704512495148854}, {"country_id": "MY", "probability": 0.2954875048511461}]}
{"name": "parthipan", "country": []}
{"name": "partho", "country": [{"country_id": "IN", "probability": 1}]}
{"name": "partibha", "country": []}
{"name": "partida", "country": []}
{"name": "partini", "country": []}
{"name": "parul", "country": [{"country_id": "IN", "probability": 1}]}
{"name": "parvana", "country": [{"country_id": "AZ", "probability": 1}]}
{"name": "parvaneh", "country": [{"country_id": "IR", "probability": 1}]}
{"name": "parvathi", "country": [{"country_id": "IN", "probability": 1}]}
{"name": "parvati", "country": []}
{"name": "parveen", "country": [{"country_id": "IN", "probability": 0.9583283109677625}, {"country_id": "GB", "probability": 0.041671689032237585}]}
{"name": "parvesh", "country": [{"country_id": "IN", "probability": 1}]}
{"name": "parvin", "country": [{"country_id": "AZ", "probability": 0.6292168597066072}, {"country_id": "IR", "probability": 0.37078314029339304}]}
{"name": "parvina", "country": [{"country_id": "TJ", "probability": 1}]}
{"name": "parviz", "country": [{"country_id": "TJ", "probability": 0.761839046754699}, {"country_id": "AZ", "probability": 0.1611617120075327}, {"country_id": "IR", "probability": 0.07430443668523681}]}
{"name": "parwitaningsih", "country": []}
{"name": "pasachol", "country": []}
{"name": "pascal", "country": [{"country_id": "BI", "probability": 0.06319258257037892}, {"country_id": "FR", "probability": 0.05939408988148121}, {"country_id": "RE", "probability": 0.05690011881810014}]}
{"name": "pascale", "country": [{"country_id": "BE", "probability": 0.19442787991691873}, {"country_id": "FR", "probability": 0.13657193792990183}, {"country_id": "LU", "probability": 0.13410228585739714}]}
{"name": "pascaline", "country": [{"country_id": "BF", "probability": 0.1788705049813971}, {"country_id": "CM", "probability": 0.13955124748147704}, {"country_id": "MU", "probability": 0.13654908547109904}]}
{"name": "paschal", "country": [{"country_id": "TZ", "probability": 0.7086433310345354}, {"country_id": "NG", "probability": 0.28220470824617366}, {"country_id": "GB", "probability": 0.009151960719290954}]}
{"name": "pascu", "country": [{"country_id": "RO", "probability": 0.8535720430525927}, {"country_id": "", "probability": 0.07117099389335109}, {"country_id": "ES", "probability": 0.06030070507722156}]}
{"name": "pascual", "country": [{"country_id": "GQ", "probability": 0.8738335591813952}, {"country_id": "ES", "probability": 0.09621424841674492}, {"country_id": "PH", "probability": 0.016603005361433998}]}
{"name": "pasi", "country": [{"country_id": "FI", "probability": 0.9656964538117616}, {"country_id": "SE", "probability": 0.0189566377307823}, {"country_id": "HU", "probability": 0.007122004987932647}]}
{"name": "pasian", "country": []}
{"name": "pasno", "country": []}
{"name": "pasqual", "country": [{"country_id": "DE", "probability": 0.5395789329146282}, {"country_id": "ES", "probability": 0.17403481643161867}, {"country_id": "FR", "probability": 0.15043039672644393}]}
{"name": "pasquale", "country": [{"country_id": "IT", "probability": 0.6697765322948164}, {"country_id": "", "probability": 0.15489410059785716}, {"country_id": "CH", "probability": 0.06416444842534409}]}
{"name": "pasqualina", "country": [{"country_id": "IT", "probability": 0.677479093844553}, {"country_id": "", "probability": 0.2690414346027165}, {"country_id": "DE", "probability": 0.053479471552730556}]}
{"name": "pasqueline", "country": []}
{"name": "pasquina", "country": [{"country_id": "IT", "probability": 1}]}
{"name": "passant", "country": [{"country_id": "EG", "probability": 1}]}
{"name": "passarella", "country": []}
{"name": "passawan", "country": []}
{"name": "passiante", "country": []}
{"name": "pastora", "country": [{"country_id": "ES", "probability": 1.0000000000000002}]}
{"name": "pasu", "country": []}
{"name": "pasukat", "country": []}
{"name": "paswel", "country": []}
{"name": "pat", "country": [{"country_id": "IE", "probability": 0.13217360436263512}, {"country_id": "TH", "probability": 0.0794059905084032}, {"country_id": "CA", "probability": 0.0656172958789285}]}
{"name": "patama", "country": []}
{"name": "patamaporn", "country": []}
{"name": "patanjali", "country": []}
{"name": "patara", "country": []}
{"name": "pataraporn", "country": []}
{"name": "patare", "country": []}
{"name": "patchapoom", "country": []}
{"name": "patcharaporn", "country": [{"country_id": "TH", "probability": 0.9999999999999999}]}
{"name": "patcharawadee", "country": []}
{"name": "patchareeya", "country": []}
{"name": "patcharin", "country": [{"country_id": "TH", "probability": 1}]}
{"name": "patel", "country": [{"country_id": "IN", "probability": 0.5149389262332112}, {"country_id": "UG", "probability": 0.4105537407170953}, {"country_id": "ZA", "probability": 0.05373114463539179}]}
{"name": "patelmilan", "country": []}
{"name": "pater", "country": [{"country_id": "ES", "probability": 1.0000000000000002}]}
{"name": "paternostro", "country": []}
{"name": "pathik", "country": []}
{"name": "pathompong", "country": [{"country_id": "TH", "probability": 0.9999999999999999}]}
{"name": "pathricia", "country": []}
{"name": "patience", "country": [{"country_id": "ZW", "probability": 0.37419218597276294}, {"country_id": "BW", "probability": 0.14142298589477106}, {"country_id": "GH", "probability": 0.12793497946698515}]}
{"name": "patient", "country": [{"country_id": "CD", "probability": 0.9328060029457368}, {"country_id": "CM", "probability": 0.06719399705426322}]}
{"name": "patil", "country": [{"country_id": "IN", "probability": 1}]}
{"name": "patinya", "country": [{"country_id": "TH", "probability": 1}]}
{"name": "patipan", "country": []}
{"name": "patipat", "country": [{"country_id": "TH", "probability": 1}]}
{"name": "patiyuth", "country": []}
{"name": "patlolla", "country": []}
{"name": "patou", "country": [{"country_id": "CD", "probability": 0.3519888819896579}, {"country_id": "CM", "probability": 0.19626051154197288}, {"country_id": "RE", "probability": 0.19482745020494596}]}
{"name": "patrali", "country": []}
{"name": "patrcik", "country": []}
{"name": "patreece", "country": []}
{"name": "patri", "country": [{"country_id": "ES", "probability": 0.7623232206908065}, {"country_id": "AR", "probability": 0.1596249132503107}, {"country_id": "", "probability": 0.026154568394119924}]}
{"name": "patria", "country": [{"country_id": "ID", "probability": 0.6866473212210579}, {"country_id": "PH", "probability": 0.31335267877894213}]}
{"name": "patric", "country": [{"country_id": "SE", "probability": 0.389034124731403}, {"country_id": "CH", "probability": 0.1805269667476228}, {"country_id": "DE", "probability": 0.10770979514641761}]}
{"name": "patrice", "country": [{"country_id": "GP", "probability": 0.11265508982088407}, {"country_id": "GF", "probability": 0.1080740062610361}, {"country_id": "MQ", "probability": 0.09261436385609739}]}
{"name": "patriceanne", "country": []}
{"name": "patricelouis", "country": []}
{"name": "patricia", "country": [{"country_id": "PT", "probability": 0.04603090507700609}, {"country_id": "VE", "probability": 0.036802141295459535}, {"country_id": "UY", "probability": 0.03241770728723668}]}
{"name": "patriciamarisol", "country": []}
{"name": "patricija", "country": [{"country_id": "SI", "probability": 0.8056407728855913}, {"country_id": "HR", "probability": 0.18527439602757523}, {"country_id": "", "probability": 0.009084831086833382}]}
{"name": "patricio", "country": [{"country_id": "CL", "probability": 0.38987741658221864}, {"country_id": "EC", "probability": 0.37657023463354183}, {"country_id": "AR", "probability": 0.08090858441126376}]}
{"name": "patriciomauricio", "country": []}
{"name": "patrick", "country": [{"country_id": "CD", "probability": 0.06942901966955586}, {"country_id": "LU", "probability": 0.034612273985774336}, {"country_id": "MW", "probability": 0.03412394353316552}]}
{"name": "patrickyves", "country": []}
{"name": "patrik", "country": [{"country_id": "SE", "probability": 0.30782580889978367}, {"country_id": "SK", "probability": 0.23029015809053172}, {"country_id": "CZ", "probability": 0.14751265968995983}]}
{"name": "patrili", "country": []}
{"name": "patris", "country": [{"country_id": "FR", "probability": 1}]}
{"name": "patrivan", "country": []}
{"name": "patrizia", "country": [{"country_id": "IT", "probability": 0.4458941625187648}, {"country_id": "", "probability": 0.2444680023132289}, {"country_id": "CH", "probability": 0.13177915755054187}]}
{"name": "patrizio", "country": [{"country_id": "IT", "probability": 0.6375930087045565}, {"country_id": "", "probability": 0.13469807430298794}, {"country_id": "CH", "probability": 0.1201633650178338}]}
{"name": "patrocinio", "country": [{"country_id": "PH", "probability": 0.7607972070845919}, {"country_id": "ES", "probability": 0.23920279291540805}]}
{"name": "patrycja", "country": [{"country_id": "PL", "probability": 0.7615539600428471}, {"country_id": "IE", "probability": 0.08094078426487299}, {"country_id": "", "probability": 0.05876812721576656}]}
{"name": "patryk", "country": [{"country_id": "PL", "probability": 0.6548895465947017}, {"country_id": "IS", "probability": 0.10072454506430564}, {"country_id": "IE", "probability": 0.0718223105504132}]}
{"name": "patsy", "country": [{"country_id": "IE", "probability": 0.2825288148396428}, {"country_id": "BE", "probability": 0.2569725314540282}, {"country_id": "US", "probability": 0.22898566718061766}]}
{"name": "patt", "country": [{"country_id": "TH", "probability": 0.8338392975063487}, {"country_id": "ES", "probability": 0.06665090380849603}, {"country_id": "FR", "probability": 0.05611313774278293}]}
{"name": "pattabhi", "country": []}
{"name": "pattabiraman", "country": []}
{"name": "pattama", "country": [{"country_id": "TH", "probability": 1.0000000000000002}]}
{"name": "pattanee", "country": []}
{"name": "pattarakun", "country": []}
{"name": "pattarawan", "country": []}
{"name": "pattarida", "country": []}
{"name": "patterson", "country": []}
{"name": "patthanan", "country": []}
{"name": "pattharawin", "country": []}
{"name": "patti", "country": [{"country_id": "US", "probability": 0.3495793656867655}, {"country_id": "CA", "probability": 0.305452046590651}, {"country_id": "DE", "probability": 0.08131921993851127}]}
{"name": "pattie", "country": [{"country_id": "TH", "probability": 0.6366663732290547}, {"country_id": "US", "probability": 0.3633336267709453}]}
{"name": "pattiselanno", "country": []}
{"name": "pattraporn", "country": []}
{"name": "pattulingam", "country": []}
{"name": "patty", "country": [{"country_id": "EC", "probability": 0.1744819894992034}, {"country_id": "PE", "probability": 0.10843280010481092}, {"country_id": "CL", "probability": 0.09401366638046856}]}
{"name": "patxi", "country": [{"country_id": "ES", "probability": 0.9366624635582924}, {"country_id": "FR", "probability": 0.06333753644170752}]}
{"name": "pau", "country": [{"country_id": "AR", "probability": 0.2668893434453841}, {"country_id": "ES", "probability": 0.24779724796344074}, {"country_id": "CL", "probability": 0.2146237150897371}]}
{"name": "pauchen", "country": []}
{"name": "pauchoo", "country": []}
{"name": "paul", "country": [{"country_id": "JE", "probability": 0.05723684882841736}, {"country_id": "GI", "probability": 0.05028482556828555}, {"country_id": "GB", "probability": 0.05024121425586239}]}
{"name": "paula", "country": [{"country_id": "PT", "probability": 0.13926669696218769}, {"country_id": "CO", "probability": 0.05140352028121603}, {"country_id": "FI", "probability": 0.04744738409749436}]}
{"name": "paulalexandre", "country": []}
{"name": "paulalexandru", "country": []}
{"name": "paulandre", "country": []}
{"name": "paulantoine", "country": []}
{"name": "paularmand", "country": []}
{"name": "paule", "country": [{"country_id": "CM", "probability": 0.37786565742097594}, {"country_id": "GA", "probability": 0.3495621624098046}, {"country_id": "CI", "probability": 0.19072439564842003}]}
{"name": "paulemile", "country": []}
{"name": "paulette", "country": [{"country_id": "CM", "probability": 0.34780404436176626}, {"country_id": "BE", "probability": 0.15162230504855684}, {"country_id": "FR", "probability": 0.12965052350446493}]}
{"name": "paulhermann", "country": []}
{"name": "pauli", "country": [{"country_id": "FI", "probability": 0.5523671892463038}, {"country_id": "CL", "probability": 0.2415258123317452}, {"country_id": "AR", "probability": 0.07286420465202785}]}
{"name": "pauliac", "country": []}
{"name": "paulien", "country": [{"country_id": "NL", "probability": 0.7752239947723054}, {"country_id": "BE", "probability": 0.22477600522769461}]}
{"name": "paulin", "country": [{"country_id": "CD", "probability": 0.27838490494031726}, {"country_id": "BJ", "probability": 0.15090941418619297}, {"country_id": "TG", "probability": 0.14804156042306832}]}
{"name": "paulina", "country": [{"country_id": "PL", "probability": 0.4948877349055795}, {"country_id": "CL", "probability": 0.09509765176268459}, {"country_id": "IE", "probability": 0.05197687027523199}]}
{"name": "pauline", "country": [{"country_id": "FR", "probability": 0.1116308853936964}, {"country_id": "KE", "probability": 0.09345350132632495}, {"country_id": "MT", "probability": 0.0808793061399759}]}
{"name": "paulino", "country": [{"country_id": "MZ", "probability": 0.3420450017425722}, {"country_id": "CV", "probability": 0.3157114887179195}, {"country_id": "AO", "probability": 0.27931558339390355}]}
{"name": "paulita", "country": [{"country_id": "CL", "probability": 0.444287824993195}, {"country_id": "AR", "probability": 0.21842583360862594}, {"country_id": "CO", "probability": 0.21791680348130682}]}
{"name": "paulius", "country": [{"country_id": "LT", "probability": 0.9623674413898047}, {"country_id": "IE", "probability": 0.0289286298912719}, {"country_id": "GB", "probability": 0.008703928718923499}]}
{"name": "paulo", "country": [{"country_id": "PT", "probability": 0.24780484730192842}, {"country_id": "AO", "probability": 0.1292383480342294}, {"country_id": "BR", "probability": 0.1289455160638799}]}
{"name": "paulraj", "country": []}
{"name": "paulstefan", "country": []}
{"name": "paulus", "country": [{"country_id": "ID", "probability": 0.6818437385431672}, {"country_id": "NL", "probability": 0.23773817863458274}, {"country_id": "BE", "probability": 0.051452054508673385}]}
{"name": "paulwaie", "country": []}
{"name": "paulyne", "country": [{"country_id": "FR", "probability": 1}]}
{"name": "paun", "country": [{"country_id": "RO", "probability": 0.9273814349846005}, {"country_id": "", "probability": 0.0653894975484242}, {"country_id": "IT", "probability": 0.007229067466975352}]}
{"name": "paurav", "country": []}
{"name": "pauric", "country": [{"country_id": "IE", "probability": 1}]}
{"name": "paurush", "country": []}
{"name": "pauwke", "country": []}
{"name": "pauzi", "country": []}
{"name": "pavan", "country": [{"country_id": "IN", "probability": 0.973269865774387}, {"country_id": "US", "probability": 0.01667949421907502}, {"country_id": "GB", "probability": 0.010050640006537916}]}
{"name": "pavani", "country": [{"country_id": "IN", "probability": 1}]}
{"name": "pavankumar", "country": [{"country_id": "IN", "probability": 1}]}
{"name": "pavao", "country": []}
{"name": "pavarit", "country": []}
{"name": "pavel", "country": [{"country_id": "CZ", "probability": 0.46694852858549146}, {"country_id": "EE", "probability": 0.07094788651350915}, {"country_id": "BY", "probability": 0.062260641651061134}]}
{"name": "paves", "country": []}
{"name": "pavica", "country": []}
{"name": "pavida", "country": []}
{"name": "pavita", "country": []}
{"name": "pavitar", "country": []}
{"name": "pavithra", "country": [{"country_id": "IN", "probability": 1}]}
{"name": "pavitra", "country": []}
{"name": "pavla", "country": [{"country_id": "CZ", "probability": 0.9497767707552797}, {"country_id": "SK", "probability": 0.04191265566044841}, {"country_id": "GB", "probability": 0.0036444063099169755}]}
{"name": "pavle", "country": [{"country_id": "ME", "probability": 0.537789697794512}, {"country_id": "RS", "probability": 0.2644484413973055}, {"country_id": "HR", "probability": 0.10904475070858943}]}
{"name": "pavlidis", "country": []}
{"name": "pavlin", "country": [{"country_id": "BG", "probability": 1}]}
{"name": "pavlina", "country": [{"country_id": "CZ", "probability": 0.42255375986860166}, {"country_id": "BG", "probability": 0.2902847013484369}, {"country_id": "CY", "probability": 0.16666637614897414}]}
{"name": "pavlinka", "country": [{"country_id": "CZ", "probability": 0.9999999999999999}]}
{"name": "pavlo", "country": [{"country_id": "UA", "probability": 0.9512841042828044}, {"country_id": "DE", "probability": 0.020410675656082445}, {"country_id": "ES", "probability": 0.019004397131890446}]}
{"name": "pavlos", "country": [{"country_id": "CY", "probability": 0.6239777660881337}, {"country_id": "GR", "probability": 0.3572708199586962}, {"country_id": "CZ", "probability": 0.00612225866824608}]}
{"name": "pavlovich", "country": []}
{"name": "pavnit", "country": []}
{"name": "pavol", "country": [{"country_id": "SK", "probability": 0.9450801168341287}, {"country_id": "IE", "probability": 0.02442710113200184}, {"country_id": "CZ", "probability": 0.02218295067829211}]}
{"name": "pawan", "country": [{"country_id": "NP", "probability": 0.5922429539152151}, {"country_id": "IN", "probability": 0.4039605701191482}, {"country_id": "GB", "probability": 0.0037964759656367838}]}
{"name": "pawanrat", "country": []}
{"name": "pawar", "country": []}
{"name": "pawat", "country": [{"country_id": "TH", "probability": 1}]}
{"name": "pawde", "country": []}
{"name": "paweena", "country": [{"country_id": "TH", "probability": 1}]}
{"name": "pawei", "country": []}
{"name": "pawel", "country": [{"country_id": "PL", "probability": 0.3468221788928576}, {"country_id": "IE", "probability": 0.22488776100317076}, {"country_id": "IS", "probability": 0.10871806244178477}]}
{"name": "pawin", "country": [{"country_id": "TH", "probability": 1}]}
{"name": "paxton", "country": []}
{"name": "payal", "country": [{"country_id": "IN", "probability": 1}]}
{"name": "payam", "country": [{"country_id": "IR", "probability": 0.9821107460967639}, {"country_id": "SE", "probability": 0.011206183409464478}, {"country_id": "DE", "probability": 0.0034963536732214254}]}
{"name": "payas", "country": []}
{"name": "payel", "country": [{"country_id": "IN", "probability": 1}]}
{"name": "payman", "country": [{"country_id": "IR", "probability": 1}]}
{"name": "paymun", "country": []}
{"name": "payton", "country": [{"country_id": "GB", "probability": 1.0000000000000002}]}
{"name": "paz", "country": [{"country_id": "CL", "probability": 0.5558180837460194}, {"country_id": "ES", "probability": 0.19257257546470236}, {"country_id": "AR", "probability": 0.12775680369375805}]}
{"name": "pazit", "country": []}
{"name": "pazo", "country": []}
{"name": "pdt", "country": []}
{"name": "peace", "country": [{"country_id": "IO", "probability": 0.9085356042550861}, {"country_id": "LR", "probability": 0.06010627977445971}, {"country_id": "UG", "probability": 0.00799681789693292}]}
{"name": "peam", "country": []}
{"name": "pearce", "country": []}
{"name": "pearila", "country": []}
{"name": "pearl", "country": [{"country_id": "BW", "probability": 0.4376455510912011}, {"country_id": "GH", "probability": 0.12833580049796833}, {"country_id": "ZA", "probability": 0.11649014628919853}]}
{"name": "pearlman", "country": []}
{"name": "pease", "country": []}
{"name": "pebbles", "country": [{"country_id": "GB", "probability": 0.7925743813751676}, {"country_id": "ES", "probability": 0.20742561862483255}]}
{"name": "pechetti", "country": []}
{"name": "pechin", "country": []}
{"name": "peck", "country": [{"country_id": "SG", "probability": 0.6335573620483309}, {"country_id": "MY", "probability": 0.20474043603976202}, {"country_id": "TH", "probability": 0.15056688132072849}]}
{"name": "pecutti", "country": []}
{"name": "peda", "country": [{"country_id": "AT", "probability": 1}]}
{"name": "peddiboyina", "country": []}
{"name": "peddinti", "country": []}
{"name": "peder", "country": [{"country_id": "DK", "probability": 0.4385137569766042}, {"country_id": "NO", "probability": 0.27866554993777787}, {"country_id": "SE", "probability": 0.26839109372638853}]}
{"name": "pedram", "country": [{"country_id": "IR", "probability": 0.980106561986695}, {"country_id": "SE", "probability": 0.012667775476004704}, {"country_id": "DE", "probability": 0.0037948514511515702}]}
{"name": "pedro", "country": [{"country_id": "PT", "probability": 0.1609741759175144}, {"country_id": "AO", "probability": 0.07707425062257989}, {"country_id": "GQ", "probability": 0.053830100707688816}]}
{"name": "pedroangel", "country": []}
{"name": "peeler", "country": []}
{"name": "peep", "country": [{"country_id": "ES", "probability": 1.0000000000000002}]}
{"name": "peer", "country": [{"country_id": "DK", "probability": 0.511675746615139}, {"country_id": "NL", "probability": 0.29102144999578966}, {"country_id": "DE", "probability": 0.19730280338907139}]}
{"name": "peerapon", "country": [{"country_id": "TH", "probability": 1}]}
{"name": "peerapong", "country": [{"country_id": "TH", "probability": 1}]}
{"name": "peerapop", "country": []}
{"name": "peerayuth", "country": []}
{"name": "peertimo", "country": []}
{"name": "peertopeer", "country": []}
{"name": "peeter", "country": [{"country_id": "EE", "probability": 0.996376054047993}, {"country_id": "IT", "probability": 0.0018528673738982713}, {"country_id": "FR", "probability": 0.0017710785781087398}]}
{"name": "peg", "country": [{"country_id": "FR", "probability": 0.8563983291680725}, {"country_id": "DE", "probability": 0.14360167083192735}]}
{"name": "pegah", "country": [{"country_id": "IR", "probability": 1}]}
{"name": "pegalajar", "country": []}
{"name": "pegerto", "country": []}
{"name": "peggy", "country": [{"country_id": "TW", "probability": 0.240023510788846}, {"country_id": "BE", "probability": 0.09812048939178548}, {"country_id": "HK", "probability": 0.07334891130856018}]}
{"name": "peh", "country": [{"country_id": "SG", "probability": 0.8229477294413318}, {"country_id": "MY", "probability": 0.1770522705586684}]}
{"name": "pehn", "country": []}
{"name": "pehong", "country": []}
{"name": "pehrolov", "country": []}
{"name": "pei", "country": [{"country_id": "SG", "probability": 0.34909856851037646}, {"country_id": "MY", "probability": 0.331774755805163}, {"country_id": "TW", "probability": 0.2688675728781332}]}
{"name": "peiai", "country": []}
{"name": "peicang", "country": []}
{"name": "peichann", "country": []}
{"name": "peichao", "country": []}
{"name": "peichen", "country": []}
{"name": "peichern", "country": []}
{"name": "peichi", "country": []}
{"name": "peichia", "country": []}
{"name": "peiching", "country": []}
{"name": "peichuan", "country": []}
{"name": "peichun", "country": []}
{"name": "peide", "country": []}
{"name": "peidi", "country": []}
{"name": "peidong", "country": []}
{"name": "peiduo", "country": []}
{"name": "peifa", "country": []}
{"name": "peifang", "country": []}
{"name": "peifen", "country": []}
{"name": "peifeng", "country": []}
{"name": "peifung", "country": []}
{"name": "peigang", "country": []}
{"name": "peigen", "country": []}
{"name": "peigong", "country": []}
{"name": "peiguan", "country": []}
{"name": "peiguang", "country": []}
{"name": "peihong", "country": []}
{"name": "peihsi", "country": []}
{"name": "peihsin", "country": []}
{"name": "peihsuan", "country": []}
{"name": "peihua", "country": []}
{"name": "peihui", "country": []}
{"name": "peihung", "country": []}
{"name": "peii", "country": []}
{"name": "peiji", "country": []}
{"name": "peijian", "country": []}
{"name": "peijiang", "country": []}
{"name": "peijie", "country": []}
{"name": "peiju", "country": []}
{"name": "peijun", "country": []}
{"name": "peijung", "country": []}
{"name": "peik", "country": []}
{"name": "peikai", "country": []}
{"name": "peili", "country": []}
{"name": "peilian", "country": []}
{"name": "peiliang", "country": []}
{"name": "peilin", "country": []}
{"name": "peiling", "country": []}
{"name": "peiluan", "country": []}
{"name": "peiluen", "country": []}
{"name": "peilun", "country": []}
{"name": "peiming", "country": []}
{"name": "peinazomorales", "country": []}
{"name": "peining", "country": []}
{"name": "peio", "country": [{"country_id": "ES", "probability": 0.6604249002899018}, {"country_id": "FR", "probability": 0.33957509971009836}]}
{"name": "peipei", "country": [{"country_id": "TW", "probability": 1}]}
{"name": "peiqiang", "country": []}
{"name": "peiquan", "country": []}
{"name": "peiqun", "country": []}
{"name": "peiran", "country": []}
{"name": "peiris", "country": []}
{"name": "peirong", "country": []}
{"name": "peiru", "country": []}
{"name": "peisen", "country": []}
{"name": "peishan", "country": []}
{"name": "peishuai", "country": []}
{"name": "peisi", "country": []}
{"name": "peite", "country": []}
{"name": "peiteng", "country": []}
{"name": "peitsun", "country": []}
{"name": "peivand", "country": []}
{"name": "peiwei", "country": []}
{"name": "peiwen", "country": []}
{"name": "peixi", "country": []}
{"name": "peixiang", "country": []}
{"name": "peixin", "country": []}
{"name": "peixuan", "country": []}
{"name": "peixun", "country": []}
{"name": "peiyan", "country": []}
{"name": "peiyang", "country": []}
{"name": "peiyao", "country": []}
{"name": "peiyi", "country": []}
{"name": "peiying", "country": []}
{"name": "peiyong", "country": []}
{"name": "peiyu", "country": []}
{"name": "peiyuan", "country": []}
{"name": "peiyun", "country": []}
{"name": "peiyung", "country": []}
{"name": "peizhang", "country": []}
{"name": "peizhao", "country": []}
{"name": "peizhe", "country": []}
{"name": "peizhen", "country": []}
{"name": "peizhi", "country": []}
{"name": "peizhong", "country": []}
{"name": "peizhou", "country": []}
{"name": "peizhuang", "country": []}
{"name": "pejman", "country": [{"country_id": "IR", "probability": 0.9960396462864428}, {"country_id": "DE", "probability": 0.003960353713557151}]}
{"name": "pekhooi", "country": []}
{"name": "pekka", "country": [{"country_id": "FI", "probability": 0.9701254310617066}, {"country_id": "SE", "probability": 0.023217293899396953}, {"country_id": "", "probability": 0.006657275038896483}]}
{"name": "pekko", "country": []}
{"name": "pelau", "country": []}
{"name": "pelayo", "country": [{"country_id": "ES", "probability": 1}]}
{"name": "peldon", "country": []}
{"name": "pele", "country": [{"country_id": "TH", "probability": 0.42812846761061446}, {"country_id": "RO", "probability": 0.33090041512350543}, {"country_id": "ES", "probability": 0.10709906982558065}]}
{"name": "peleschyshyn", "country": []}
{"name": "pelillo", "country": []}
{"name": "pelin", "country": [{"country_id": "TR", "probability": 0.7006905971211244}, {"country_id": "", "probability": 0.12952293956183125}, {"country_id": "DE", "probability": 0.05499325786995823}]}
{"name": "pelinescu", "country": []}
{"name": "pelo", "country": [{"country_id": "IT", "probability": 0.4038241389554815}, {"country_id": "FR", "probability": 0.3510862640956561}, {"country_id": "ES", "probability": 0.2450895969488624}]}
{"name": "pembe", "country": [{"country_id": "TR", "probability": 0.9016822564631041}, {"country_id": "DE", "probability": 0.09831774353689587}]}
{"name": "pen", "country": [{"country_id": "TH", "probability": 0.8937432997145397}, {"country_id": "GB", "probability": 0.06546860954911587}, {"country_id": "ES", "probability": 0.015548987506382641}]}
{"name": "pena", "country": [{"country_id": "FI", "probability": 0.8623096905356793}, {"country_id": "RO", "probability": 0.13769030946432076}]}
{"name": "penchan", "country": []}
{"name": "pencho", "country": [{"country_id": "ES", "probability": 1}]}
{"name": "pendyala", "country": []}
{"name": "penelope", "country": [{"country_id": "DO", "probability": 0.24249250703536165}, {"country_id": "GR", "probability": 0.1721566989107183}, {"country_id": "ZA", "probability": 0.1151960474723957}]}
{"name": "penelopi", "country": []}
{"name": "peng", "country": [{"country_id": "CN", "probability": 0.5043556189684213}, {"country_id": "SG", "probability": 0.2359415765633978}, {"country_id": "TW", "probability": 0.13553076143822487}]}
{"name": "pengao", "country": []}
{"name": "pengbi", "country": []}
{"name": "pengbin", "country": []}
{"name": "pengbo", "country": []}
{"name": "pengcheng", "country": []}
{"name": "pengchia", "country": []}
{"name": "pengchun", "country": []}
{"name": "pengda", "country": []}
{"name": "pengdeng", "country": []}
{"name": "pengfei", "country": [{"country_id": "CN", "probability": 1}]}
{"name": "penghe", "country": []}
{"name": "penghong", "country": []}
{"name": "penghua", "country": []}
{"name": "penghui", "country": []}
{"name": "pengiran", "country": []}
{"name": "pengjen", "country": []}
{"name": "pengjian", "country": []}
{"name": "pengjiang", "country": []}
{"name": "pengjiao", "country": []}
{"name": "pengjie", "country": []}
{"name": "pengju", "country": []}
{"name": "pengjun", "country": []}
{"name": "pengkui", "country": []}
{"name": "pengkun", "country": []}
{"name": "pengli", "country": []}
{"name": "pengliu", "country": []}
{"name": "pengmin", "country": []}
{"name": "pengpeng", "country": [{"country_id": "CN", "probability": 1}]}
{"name": "pengren", "country": []}
{"name": "pengsee", "country": []}
{"name": "pengsen", "country": []}
{"name": "pengsheng", "country": []}
{"name": "pengshuai", "country": []}
{"name": "pengsu", "country": []}
{"name": "pengwei", "country": []}
{"name": "pengxi", "country": []}
{"name": "pengxiang", "country": []}
{"name": "pengya", "country": []}
{"name": "pengyan", "country": []}
{"name": "pengyao", "country": []}
{"name": "pengye", "country": []}
{"name": "pengyi", "country": []}
{"name": "pengyu", "country": []}
{"name": "pengyuan", "country": []}
{"name": "pengzhen", "country": []}
{"name": "pengzhi", "country": []}
{"name": "pengzhu", "country": []}
{"name": "penin", "country": [{"country_id": "FR", "probability": 1}]}
{"name": "penina", "country": [{"country_id": "KE", "probability": 1}]}
{"name": "peninah", "country": [{"country_id": "KE", "probability": 1}]}
{"name": "penjira", "country": []}
{"name": "penjung", "country": []}
{"name": "penjuree", "country": []}
{"name": "pennarun", "country": []}
{"name": "penney", "country": []}
{"name": "penni", "country": []}
{"name": "pennie", "country": [{"country_id": "US", "probability": 0.6193384263630124}, {"country_id": "GB", "probability": 0.38066157363698766}]}
{"name": "penninkilampi", "country": []}
{"name": "pennsylvania", "country": []}
{"name": "penny", "country": [{"country_id": "TW", "probability": 0.20095058415896286}, {"country_id": "GR", "probability": 0.14135136057034373}, {"country_id": "HK", "probability": 0.0889816039109012}]}
{"name": "penov", "country": []}
{"name": "penporn", "country": []}
{"name": "pensri", "country": [{"country_id": "TH", "probability": 1}]}
{"name": "pentayala", "country": []}
{"name": "pentland", "country": []}
{"name": "pentti", "country": [{"country_id": "FI", "probability": 0.9592279213431993}, {"country_id": "SE", "probability": 0.04077207865680066}]}
{"name": "penugonda", "country": []}
{"name": "penyuang", "country": []}
{"name": "penz", "country": []}
{"name": "peodair", "country": []}
{"name": "peoples", "country": []}
{"name": "pep", "country": [{"country_id": "AD", "probability": 0.7481721037805529}, {"country_id": "ES", "probability": 0.17901863642761004}, {"country_id": "CZ", "probability": 0.023761128255945965}]}
{"name": "pepa", "country": [{"country_id": "CZ", "probability": 0.572704783234945}, {"country_id": "ES", "probability": 0.18603422288300375}, {"country_id": "BG", "probability": 0.13723483656884528}]}
{"name": "pepe", "country": [{"country_id": "ES", "probability": 0.20322849236413057}, {"country_id": "AD", "probability": 0.19785328443905167}, {"country_id": "MX", "probability": 0.0885917369917019}]}
{"name": "pepijn", "country": [{"country_id": "NL", "probability": 1}]}
{"name": "pepka", "country": []}
{"name": "peppe", "country": [{"country_id": "IT", "probability": 0.8319193078796348}, {"country_id": "", "probability": 0.05695571478026327}, {"country_id": "SE", "probability": 0.03682331506007897}]}
{"name": "peppino", "country": [{"country_id": "IT", "probability": 0.8154224038977902}, {"country_id": "CH", "probability": 0.1404679979980488}, {"country_id": "DE", "probability": 0.04410959810416102}]}
{"name": "pepule", "country": []}
{"name": "pequignot", "country": []}
{"name": "per", "country": [{"country_id": "NO", "probability": 0.38686944072981655}, {"country_id": "DK", "probability": 0.3406581368548368}, {"country_id": "SE", "probability": 0.2521847435012955}]}
{"name": "perakath", "country": []}
{"name": "perake", "country": []}
{"name": "perales", "country": []}
{"name": "peranders", "country": []}
{"name": "perc", "country": []}
{"name": "perci", "country": []}
{"name": "percin", "country": []}
{"name": "percival", "country": [{"country_id": "PH", "probability": 1}]}
{"name": "percy", "country": [{"country_id": "PE", "probability": 0.6976034080806994}, {"country_id": "ZA", "probability": 0.08288757909385548}, {"country_id": "MU", "probability": 0.08018271395553024}]}
{"name": "pere", "country": [{"country_id": "AD", "probability": 0.8635662092882174}, {"country_id": "ES", "probability": 0.1156482268128742}, {"country_id": "NG", "probability": 0.018254650472965126}]}
{"name": "peredur", "country": []}
{"name": "pereira", "country": [{"country_id": "LU", "probability": 0.5044852961173433}, {"country_id": "PT", "probability": 0.24525417878106026}, {"country_id": "AO", "probability": 0.1261553961433866}]}
{"name": "perelman", "country": []}
{"name": "perez", "country": [{"country_id": "CI", "probability": 0.17720330381510213}, {"country_id": "CH", "probability": 0.15821855073902977}, {"country_id": "NG", "probability": 0.15286705254660743}]}
{"name": "perfecto", "country": [{"country_id": "PH", "probability": 0.8552139270320818}, {"country_id": "ES", "probability": 0.1447860729679182}]}
{"name": "performance", "country": []}
{"name": "perger", "country": []}
{"name": "perianayagam", "country": []}
{"name": "periasamy", "country": []}
{"name": "perihan", "country": [{"country_id": "TR", "probability": 0.7001890713277303}, {"country_id": "", "probability": 0.2395066801417665}, {"country_id": "DE", "probability": 0.06030424853050322}]}
{"name": "perika", "country": []}
{"name": "periklis", "country": [{"country_id": "GR", "probability": 1}]}
{"name": "pering", "country": []}
{"name": "peris", "country": [{"country_id": "KE", "probability": 0.8466520374674729}, {"country_id": "GR", "probability": 0.14962637856366412}, {"country_id": "ES", "probability": 0.003721583968862953}]}
{"name": "periwinkle", "country": []}
{"name": "perju", "country": [{"country_id": "RO", "probability": 1}]}
{"name": "perla", "country": [{"country_id": "DO", "probability": 0.2904105361000028}, {"country_id": "MX", "probability": 0.20059089935121918}, {"country_id": "LB", "probability": 0.09614720949274976}]}
{"name": "perman", "country": []}
{"name": "permanand", "country": []}
{"name": "permata", "country": [{"country_id": "ID", "probability": 1}]}
{"name": "permathias", "country": []}
{"name": "perminder", "country": []}
{"name": "pern", "country": []}
{"name": "pernghwa", "country": []}
{"name": "pernilla", "country": [{"country_id": "SE", "probability": 0.9887761751876691}, {"country_id": "", "probability": 0.011223824812330984}]}
{"name": "pernille", "country": [{"country_id": "DK", "probability": 0.919526477602487}, {"country_id": "NO", "probability": 0.04730029387888151}, {"country_id": "", "probability": 0.03317322851863158}]}
{"name": "pernilly", "country": []}
{"name": "pero", "country": [{"country_id": "HR", "probability": 0.44204336754486995}, {"country_id": "ME", "probability": 0.14727568008703953}, {"country_id": "BA", "probability": 0.12041504335428145}]}
{"name": "perola", "country": [{"country_id": "PT", "probability": 0.9110270805101761}, {"country_id": "IT", "probability": 0.0889729194898238}]}
{"name": "peroli", "country": []}
{"name": "perolof", "country": []}
{"name": "perotti", "country": []}
{"name": "perouz", "country": []}
{"name": "perpetua", "country": [{"country_id": "NG", "probability": 0.5091868242226824}, {"country_id": "PH", "probability": 0.49081317577731765}]}
{"name": "perpetuo", "country": []}
{"name": "perri", "country": [{"country_id": "ES", "probability": 0.6407834034152496}, {"country_id": "IT", "probability": 0.3592165965847503}]}
{"name": "perrig", "country": []}
{"name": "perrin", "country": [{"country_id": "FR", "probability": 1}]}
{"name": "perrine", "country": [{"country_id": "MU", "probability": 0.40028302947861166}, {"country_id": "FR", "probability": 0.35411697285245275}, {"country_id": "BE", "probability": 0.15560903721564465}]}
{"name": "perrucci", "country": []}
{"name": "perry", "country": [{"country_id": "GH", "probability": 0.14664627655464366}, {"country_id": "CA", "probability": 0.13714188821274004}, {"country_id": "US", "probability": 0.12721033586772387}]}
{"name": "persa", "country": [{"country_id": "GR", "probability": 0.604951454903204}, {"country_id": "RS", "probability": 0.3950485450967959}]}
{"name": "persi", "country": []}
{"name": "persis", "country": []}
{"name": "pertti", "country": [{"country_id": "FI", "probability": 0.9706684908555}, {"country_id": "SE", "probability": 0.029331509144499893}]}
{"name": "perttu", "country": [{"country_id": "FI", "probability": 1}]}
{"name": "peru", "country": [{"country_id": "ES", "probability": 0.7179546159971518}, {"country_id": "IT", "probability": 0.28204538400284823}]}
{"name": "peruvemba", "country": []}
{"name": "pervaiz", "country": [{"country_id": "PK", "probability": 1}]}
{"name": "perver", "country": []}
{"name": "pervez", "country": [{"country_id": "PK", "probability": 1}]}
{"name": "pescosolido", "country": []}
{"name": "peshawa", "country": []}
{"name": "pesquisadora", "country": []}
{"name": "peta", "country": [{"country_id": "CZ", "probability": 0.5973884934058041}, {"country_id": "SK", "probability": 0.33210865553472857}, {"country_id": "RO", "probability": 0.03079961800092717}]}
{"name": "petar", "country": [{"country_id": "ME", "probability": 0.2796343998910678}, {"country_id": "RS", "probability": 0.21843473328591528}, {"country_id": "HR", "probability": 0.15942980837938062}]}
{"name": "petburi", "country": []}
{"name": "pete", "country": [{"country_id": "GB", "probability": 0.23203069191764758}, {"country_id": "FI", "probability": 0.1867512871280106}, {"country_id": "IE", "probability": 0.07993569234239206}]}
{"name": "petek", "country": [{"country_id": "TR", "probability": 0.8416561749317845}, {"country_id": "DE", "probability": 0.1583438250682156}]}
{"name": "peter", "country": [{"country_id": "SK", "probability": 0.1245678651196634}, {"country_id": "AU", "probability": 0.04147520566025031}, {"country_id": "KE", "probability": 0.04107488447822492}]}
{"name": "peteris", "country": [{"country_id": "LV", "probability": 1}]}
{"name": "peterlin", "country": []}
{"name": "peterpaul", "country": []}
{"name": "peterson", "country": [{"country_id": "KE", "probability": 0.3783840906212152}, {"country_id": "AO", "probability": 0.2528493186367364}, {"country_id": "BR", "probability": 0.2285686633175234}]}
{"name": "petia", "country": [{"country_id": "BG", "probability": 1}]}
{"name": "petite", "country": [{"country_id": "RE", "probability": 0.3721243748619769}, {"country_id": "FR", "probability": 0.20444164459439793}, {"country_id": "BE", "probability": 0.12925845155668228}]}
{"name": "petja", "country": [{"country_id": "FI", "probability": 0.9447224136333894}, {"country_id": "DE", "probability": 0.05527758636661059}]}
{"name": "petko", "country": [{"country_id": "BG", "probability": 0.8434341977416073}, {"country_id": "SK", "probability": 0.1565658022583926}]}
{"name": "petla", "country": []}
{"name": "petr", "country": [{"country_id": "CZ", "probability": 0.9297110436349095}, {"country_id": "SK", "probability": 0.020626425572414803}, {"country_id": "IE", "probability": 0.010779090754648555}]}
{"name": "petra", "country": [{"country_id": "CZ", "probability": 0.31955076580460245}, {"country_id": "SI", "probability": 0.13680945087241525}, {"country_id": "SK", "probability": 0.11955853322823035}]}
{"name": "petre", "country": [{"country_id": "RO", "probability": 0.9229595112053456}, {"country_id": "", "probability": 0.04258775388852648}, {"country_id": "GB", "probability": 0.01081098441561781}]}
{"name": "petrea", "country": [{"country_id": "MD", "probability": 0.5928047498275142}, {"country_id": "RO", "probability": 0.39871666724901716}, {"country_id": "IT", "probability": 0.008478582923468661}]}
{"name": "petrescu", "country": [{"country_id": "RO", "probability": 0.9934024472139703}, {"country_id": "IT", "probability": 0.006597552786029677}]}
{"name": "petri", "country": [{"country_id": "FI", "probability": 0.9441774193216336}, {"country_id": "SE", "probability": 0.033715214881607135}, {"country_id": "", "probability": 0.007111135083669456}]}
{"name": "petrica", "country": [{"country_id": "RO", "probability": 0.9174677043019973}, {"country_id": "", "probability": 0.04899160118060542}, {"country_id": "IT", "probability": 0.019259424033511482}]}
{"name": "petrie", "country": []}
{"name": "petrik", "country": [{"country_id": "SK", "probability": 0.48384363496002797}, {"country_id": "HU", "probability": 0.2503716700968926}, {"country_id": "RO", "probability": 0.15198396596072633}]}
{"name": "petrilson", "country": []}
{"name": "petrisor", "country": [{"country_id": "RO", "probability": 0.9749536191977234}, {"country_id": "IT", "probability": 0.014745611818086002}, {"country_id": "ES", "probability": 0.010300768984190696}]}
{"name": "petro", "country": [{"country_id": "ZA", "probability": 0.327856267990261}, {"country_id": "UA", "probability": 0.2402010901857134}, {"country_id": "AL", "probability": 0.15267293738649523}]}
{"name": "petroleum", "country": []}
{"name": "petromil", "country": []}
{"name": "petronella", "country": [{"country_id": "ZA", "probability": 0.3150351806383707}, {"country_id": "SE", "probability": 0.2578607053820857}, {"country_id": "HU", "probability": 0.2511978615434492}]}
{"name": "petros", "country": [{"country_id": "CY", "probability": 0.50508485907032}, {"country_id": "GR", "probability": 0.47750177427170515}, {"country_id": "", "probability": 0.005550546253509103}]}
{"name": "petrosstylianos", "country": []}
{"name": "petrou", "country": []}
{"name": "petroula", "country": [{"country_id": "GR", "probability": 1}]}
{"name": "petrova", "country": []}
{"name": "petru", "country": [{"country_id": "MD", "probability": 0.7613719689994051}, {"country_id": "RO", "probability": 0.1986466259765233}, {"country_id": "", "probability": 0.015044853402078118}]}
{"name": "petrucio", "country": []}
{"name": "petrus", "country": [{"country_id": "NA", "probability": 0.6731257089106952}, {"country_id": "ZA", "probability": 0.09889146255974582}, {"country_id": "ID", "probability": 0.09202501691957825}]}
{"name": "petruta", "country": [{"country_id": "RO", "probability": 0.9646903952152338}, {"country_id": "IT", "probability": 0.01934161488195168}, {"country_id": "ES", "probability": 0.015967989902814398}]}
{"name": "petry", "country": [{"country_id": "RO", "probability": 0.7871804888983075}, {"country_id": "ES", "probability": 0.2128195111016923}]}
{"name": "petter", "country": [{"country_id": "NO", "probability": 0.7677090115975607}, {"country_id": "SE", "probability": 0.22877011901293212}, {"country_id": "ES", "probability": 0.0029643125789534097}]}
{"name": "petteri", "country": [{"country_id": "FI", "probability": 1.0000000000000002}]}
{"name": "pettersson", "country": []}
{"name": "petulla", "country": []}
{"name": "petya", "country": [{"country_id": "BG", "probability": 0.8230204029964275}, {"country_id": "HU", "probability": 0.12638087207492432}, {"country_id": "UA", "probability": 0.03141318518444682}]}
{"name": "pew", "country": []}
{"name": "peyam", "country": []}
{"name": "peyina", "country": []}
{"name": "peyman", "country": [{"country_id": "IR", "probability": 0.979783027653507}, {"country_id": "SE", "probability": 0.010123137632654291}, {"country_id": "DE", "probability": 0.004634668899613865}]}
{"name": "peyrols", "country": []}
{"name": "peysakhovich", "country": []}
{"name": "peyton", "country": [{"country_id": "US", "probability": 0.5860096600353248}, {"country_id": "GB", "probability": 0.23540970151772952}, {"country_id": "FR", "probability": 0.0961937167864715}]}
{"name": "pezeril", "country": []}
{"name": "pezeshki", "country": []}
{"name": "pezhman", "country": [{"country_id": "IR", "probability": 1}]}
{"name": "pezzuti", "country": []}
{"name": "pfeiffer", "country": [{"country_id": "FR", "probability": 1}]}
{"name": "pgce", "country": []}
{"name": "ph", "country": [{"country_id": "VN", "probability": 0.9925080360553098}, {"country_id": "FR", "probability": 0.002808792152908215}, {"country_id": "GB", "probability": 0.002724022693001213}]}
{"name": "phadatare", "country": []}
{"name": "phadre", "country": []}
{"name": "phaedonstelios", "country": []}
{"name": "phaedra", "country": [{"country_id": "BE", "probability": 1}]}
{"name": "phaengnitta", "country": []}
{"name": "phaifa", "country": []}
{"name": "phakit", "country": []}
{"name": "phakpoom", "country": []}
{"name": "phalak", "country": []}
{"name": "phalguni", "country": []}
{"name": "phalke", "country": []}
{"name": "phalpheaktra", "country": []}
{"name": "pham", "country": [{"country_id": "VN", "probability": 0.9996915476311647}, {"country_id": "FR", "probability": 0.00030845236883525717}]}
{"name": "phammuoi", "country": []}
{"name": "phan", "country": [{"country_id": "VN", "probability": 0.9745465259335064}, {"country_id": "TH", "probability": 0.01744498523933302}, {"country_id": "MY", "probability": 0.007092230163335534}]}
{"name": "phanee", "country": []}
{"name": "phani", "country": [{"country_id": "IN", "probability": 1}]}
{"name": "phanida", "country": [{"country_id": "TH", "probability": 1}]}
{"name": "phanindra", "country": []}
{"name": "phanish", "country": []}
{"name": "phanminh", "country": []}
{"name": "phanthuan", "country": []}
{"name": "phanugorn", "country": []}
{"name": "pharmd", "country": []}
{"name": "phat", "country": [{"country_id": "VN", "probability": 0.702625623208559}, {"country_id": "TH", "probability": 0.2673149382811016}, {"country_id": "US", "probability": 0.030059438510339473}]}
{"name": "phatchayathit", "country": []}
{"name": "phathinan", "country": []}
{"name": "phayat", "country": []}
{"name": "phayung", "country": []}
{"name": "phebe", "country": [{"country_id": "PH", "probability": 1}]}
{"name": "phefumula", "country": []}
{"name": "phelipe", "country": []}
{"name": "phelps", "country": []}
{"name": "phen", "country": [{"country_id": "TH", "probability": 1}]}
{"name": "pheni", "country": []}
{"name": "phepale", "country": []}
{"name": "phesi", "country": []}
{"name": "phi", "country": [{"country_id": "VN", "probability": 0.9216315644321845}, {"country_id": "US", "probability": 0.0353764494020852}, {"country_id": "FR", "probability": 0.023240432181854582}]}
{"name": "phichayaphak", "country": []}
{"name": "phidias", "country": []}
{"name": "phijarana", "country": []}
{"name": "phil", "country": [{"country_id": "GB", "probability": 0.15265733280932806}, {"country_id": "CA", "probability": 0.0819485534418375}, {"country_id": "BE", "probability": 0.06257800660344627}]}
{"name": "philemon", "country": [{"country_id": "KE", "probability": 0.39384508509941113}, {"country_id": "CM", "probability": 0.26113033046524503}, {"country_id": "GH", "probability": 0.24343683191894414}]}
{"name": "philip", "country": [{"country_id": "SL", "probability": 0.10573169272430274}, {"country_id": "GH", "probability": 0.0866758081691821}, {"country_id": "KE", "probability": 0.07301896564385492}]}
{"name": "philipa", "country": [{"country_id": "PT", "probability": 1}]}
{"name": "philipe", "country": [{"country_id": "CI", "probability": 0.4103818660498846}, {"country_id": "FR", "probability": 0.19702730949525574}, {"country_id": "BE", "probability": 0.12045369705774413}]}
{"name": "philipos", "country": []}
{"name": "philipp", "country": [{"country_id": "AT", "probability": 0.4049381676529367}, {"country_id": "DE", "probability": 0.3914891938851753}, {"country_id": "CH", "probability": 0.15871660197384524}]}
{"name": "philippa", "country": [{"country_id": "GB", "probability": 0.9596790422435947}, {"country_id": "FR", "probability": 0.0403209577564052}]}
{"name": "philippas", "country": []}
{"name": "philippe", "country": [{"country_id": "FR", "probability": 0.10465951172051721}, {"country_id": "BE", "probability": 0.10031019484251098}, {"country_id": "GF", "probability": 0.09590487031769163}]}
{"name": "philippeantoine", "country": []}
{"name": "philippmaximilian", "country": []}
{"name": "philippos", "country": [{"country_id": "CY", "probability": 0.8378847308881224}, {"country_id": "GR", "probability": 0.1621152691118776}]}
{"name": "philips", "country": [{"country_id": "NG", "probability": 0.8814848154106624}, {"country_id": "GB", "probability": 0.05616892242032303}, {"country_id": "IT", "probability": 0.03482018678686171}]}
{"name": "phillan", "country": []}
{"name": "phillip", "country": [{"country_id": "NZ", "probability": 0.2396511192624771}, {"country_id": "AU", "probability": 0.1632046030392627}, {"country_id": "ZW", "probability": 0.1339031591902062}]}
{"name": "phillipa", "country": [{"country_id": "GB", "probability": 1}]}
{"name": "phillipe", "country": [{"country_id": "CI", "probability": 0.6683086964539154}, {"country_id": "FR", "probability": 0.17769904506602788}, {"country_id": "BE", "probability": 0.12201887879110275}]}
{"name": "phillipp", "country": [{"country_id": "DE", "probability": 1}]}
{"name": "phillippe", "country": [{"country_id": "FR", "probability": 0.5022781410601909}, {"country_id": "BE", "probability": 0.4977218589398092}]}
{"name": "philo", "country": [{"country_id": "BE", "probability": 0.5749163610033066}, {"country_id": "FR", "probability": 0.27812805385739436}, {"country_id": "DE", "probability": 0.14695558513929913}]}
{"name": "philomina", "country": [{"country_id": "GH", "probability": 0.8380842822173217}, {"country_id": "NG", "probability": 0.16191571778267838}]}
{"name": "philsik", "country": []}
{"name": "philsoo", "country": []}
{"name": "philsuk", "country": []}
{"name": "phineas", "country": []}
{"name": "phininder", "country": []}
{"name": "phionah", "country": [{"country_id": "UG", "probability": 1}]}
{"name": "phipps", "country": []}
{"name": "phisan", "country": []}
{"name": "phivos", "country": []}
{"name": "phoebe", "country": [{"country_id": "TW", "probability": 0.21342999208017022}, {"country_id": "KE", "probability": 0.17888754123651993}, {"country_id": "HK", "probability": 0.16999398993780868}]}
{"name": "phoenix", "country": [{"country_id": "TW", "probability": 0.2865501620760822}, {"country_id": "CN", "probability": 0.2057930271084028}, {"country_id": "ZA", "probability": 0.07225077331357842}]}
{"name": "phoey", "country": []}
{"name": "phokeng", "country": []}
{"name": "phokion", "country": []}
{"name": "pholasit", "country": []}
{"name": "phondanai", "country": []}
{"name": "phone", "country": [{"country_id": "MM", "probability": 1}]}
{"name": "phong", "country": [{"country_id": "VN", "probability": 0.9288809072214614}, {"country_id": "US", "probability": 0.035498194836310976}, {"country_id": "TH", "probability": 0.03258261806139696}]}
{"name": "phongphun", "country": []}
{"name": "phonkornkrit", "country": []}
{"name": "phoolgen", "country": []}
{"name": "photchanan", "country": []}
{"name": "photonics", "country": []}
{"name": "phoury", "country": []}
{"name": "phra", "country": []}
{"name": "phrakhrupipithpariyattikit", "country": []}
{"name": "phrapalad", "country": []}
{"name": "phu", "country": [{"country_id": "VN", "probability": 0.8922288624092574}, {"country_id": "TH", "probability": 0.06611836073195183}, {"country_id": "US", "probability": 0.04165277685879094}]}
{"name": "phuc", "country": [{"country_id": "VN", "probability": 0.9771786987467279}, {"country_id": "US", "probability": 0.0228213012532721}]}
{"name": "phuctran", "country": []}
{"name": "phudinan", "country": []}
{"name": "phumezo", "country": []}
{"name": "phunsak", "country": []}
{"name": "phuoc", "country": [{"country_id": "VN", "probability": 0.9723372439473319}, {"country_id": "US", "probability": 0.027662756052668113}]}
{"name": "phuong", "country": [{"country_id": "VN", "probability": 0.9710455090274199}, {"country_id": "CA", "probability": 0.01435680421988123}, {"country_id": "US", "probability": 0.012528801138816397}]}
{"name": "phuonghanh", "country": []}
{"name": "phuongthao", "country": []}
{"name": "phutthachat", "country": []}
{"name": "phyks", "country": []}
{"name": "phylis", "country": [{"country_id": "KE", "probability": 1}]}
{"name": "phyllis", "country": [{"country_id": "KE", "probability": 0.29427258788688554}, {"country_id": "GH", "probability": 0.1928480472564903}, {"country_id": "US", "probability": 0.13950676330977851}]}
{"name": "phyo", "country": [{"country_id": "MM", "probability": 0.9464179929252193}, {"country_id": "SG", "probability": 0.04868901002033476}, {"country_id": "MY", "probability": 0.0048929970544458225}]}
{"name": "phyra", "country": []}
{"name": "phys", "country": []}
{"name": "pi", "country": [{"country_id": "TH", "probability": 0.275466111786615}, {"country_id": "IT", "probability": 0.17084603870388004}, {"country_id": "CH", "probability": 0.16631697108439983}]}
{"name": "pia", "country": [{"country_id": "DK", "probability": 0.39150512860803954}, {"country_id": "FI", "probability": 0.1831761561864069}, {"country_id": "SE", "probability": 0.11460973389552058}]}
{"name": "pian", "country": [{"country_id": "ID", "probability": 1}]}
{"name": "pianpian", "country": []}
{"name": "piao", "country": [{"country_id": "CN", "probability": 0.7093879240681895}, {"country_id": "KR", "probability": 0.2906120759318105}]}
{"name": "piazzale", "country": []}
{"name": "pic", "country": [{"country_id": "FR", "probability": 0.48131625252566324}, {"country_id": "IT", "probability": 0.3687976530147786}, {"country_id": "ES", "probability": 0.14988609445955825}]}
{"name": "picariello", "country": []}
{"name": "piccoli", "country": [{"country_id": "IT", "probability": 1}]}
{"name": "pichai", "country": [{"country_id": "TH", "probability": 1}]}
{"name": "pichaya", "country": [{"country_id": "TH", "probability": 0.9999999999999999}]}
{"name": "pichen", "country": []}
{"name": "pichi", "country": [{"country_id": "ES", "probability": 1}]}
{"name": "piching", "country": []}
{"name": "pichit", "country": [{"country_id": "TH", "probability": 1}]}
{"name": "pichitchai", "country": []}
{"name": "pichitpong", "country": []}
{"name": "pichu", "country": [{"country_id": "ES", "probability": 1}]}
{"name": "pichuan", "country": []}
{"name": "pick", "country": [{"country_id": "TH", "probability": 0.9393792303539218}, {"country_id": "FR", "probability": 0.04153002830454009}, {"country_id": "IT", "probability": 0.019090741341538167}]}
{"name": "picon", "country": []}
{"name": "piechowicz", "country": []}
{"name": "piedad", "country": [{"country_id": "CO", "probability": 0.695020759405891}, {"country_id": "ES", "probability": 0.30497924059410897}]}
{"name": "piekarec", "country": []}
{"name": "pieke", "country": []}
{"name": "pier", "country": [{"country_id": "IT", "probability": 0.6262777669445234}, {"country_id": "", "probability": 0.09619196206380488}, {"country_id": "GR", "probability": 0.04631022141847013}]}
{"name": "piera", "country": [{"country_id": "IT", "probability": 0.6740326161557932}, {"country_id": "", "probability": 0.2926504519838111}, {"country_id": "DE", "probability": 0.03331693186039585}]}
{"name": "pierandre", "country": []}
{"name": "pierandrea", "country": [{"country_id": "IT", "probability": 1}]}
{"name": "pierangela", "country": [{"country_id": "IT", "probability": 1}]}
{"name": "pierangeli", "country": []}
{"name": "pierangelo", "country": [{"country_id": "IT", "probability": 0.7924223834240522}, {"country_id": "", "probability": 0.20757761657594787}]}
{"name": "pierantonio", "country": [{"country_id": "IT", "probability": 1}]}
{"name": "piercarlo", "country": [{"country_id": "IT", "probability": 1}]}
{"name": "pierce", "country": [{"country_id": "IE", "probability": 0.7495901341755337}, {"country_id": "US", "probability": 0.18052390056159667}, {"country_id": "GB", "probability": 0.05506943052966687}]}
{"name": "pierdomenico", "country": [{"country_id": "IT", "probability": 1}]}
{"name": "pieremilio", "country": []}
{"name": "pierfrancesco", "country": [{"country_id": "IT", "probability": 1}]}
{"name": "pierfranco", "country": [{"country_id": "IT", "probability": 1}]}
{"name": "piergianluca", "country": []}
{"name": "piergiorgio", "country": [{"country_id": "IT", "probability": 0.7893133620648153}, {"country_id": "", "probability": 0.21068663793518477}]}
{"name": "piergiulio", "country": [{"country_id": "IT", "probability": 1}]}
{"name": "piergiuseppe", "country": [{"country_id": "IT", "probability": 0.9999999999999999}]}
{"name": "pierline", "country": []}
{"name": "pierluca", "country": [{"country_id": "IT", "probability": 1}]}
{"name": "pierluige", "country": []}
{"name": "pierluigi", "country": [{"country_id": "IT", "probability": 0.804047223087403}, {"country_id": "", "probability": 0.1959527769125971}]}
{"name": "piermarco", "country": [{"country_id": "IT", "probability": 0.9999999999999999}]}
{"name": "piermatteo", "country": [{"country_id": "IT", "probability": 1}]}
{"name": "piermichele", "country": []}
{"name": "piero", "country": [{"country_id": "IT", "probability": 0.48820023808243074}, {"country_id": "PE", "probability": 0.24170146056317662}, {"country_id": "", "probability": 0.07858641290410202}]}
{"name": "pierpaolo", "country": [{"country_id": "IT", "probability": 0.8343191362126336}, {"country_id": "", "probability": 0.1656808637873665}]}
{"name": "pierre", "country": [{"country_id": "FR", "probability": 0.06512391394592904}, {"country_id": "CM", "probability": 0.0565435653047973}, {"country_id": "BI", "probability": 0.05358382257274293}]}
{"name": "pierrealban", "country": []}
{"name": "pierrealexandre", "country": []}
{"name": "pierreamaury", "country": []}
{"name": "pierreandre", "country": []}
{"name": "pierreanthony", "country": []}
{"name": "pierreantoine", "country": []}
{"name": "pierrebenoit", "country": []}
{"name": "pierredavid", "country": []}
{"name": "pierreedouard", "country": []}
{"name": "pierreemmanuel", "country": []}
{"name": "pierreetienne", "country": []}
{"name": "pierrefrancois", "country": []}
{"name": "pierreguillaume", "country": []}
{"name": "pierrejean", "country": [{"country_id": "FR", "probability": 1}]}
{"name": "pierrelouis", "country": []}
{"name": "pierreluc", "country": []}
{"name": "pierremarie", "country": []}
{"name": "pierremichel", "country": []}
{"name": "pierrenicolas", "country": []}
{"name": "pierreolivier", "country": []}
{"name": "pierrep", "country": []}
{"name": "pierrephilippe", "country": []}
{"name": "pierrephillippe", "country": []}
{"name": "pierrette", "country": [{"country_id": "TG", "probability": 0.24208741941880188}, {"country_id": "CM", "probability": 0.20934637199974787}, {"country_id": "BJ", "probability": 0.1607461077747211}]}
{"name": "pierrexavier", "country": []}
{"name": "pierreyves", "country": [{"country_id": "FR", "probability": 1}]}
{"name": "pierri", "country": []}
{"name": "pierrick", "country": [{"country_id": "FR", "probability": 0.4477598919053342}, {"country_id": "RE", "probability": 0.42915152843289284}, {"country_id": "CH", "probability": 0.045158125472040817}]}
{"name": "pierrot", "country": [{"country_id": "CD", "probability": 0.6258122395329021}, {"country_id": "RE", "probability": 0.1048354360661149}, {"country_id": "FR", "probability": 0.09937773032771652}]}
{"name": "piers", "country": [{"country_id": "GB", "probability": 1}]}
{"name": "piet", "country": [{"country_id": "NL", "probability": 0.7443949203878785}, {"country_id": "ZA", "probability": 0.14846541206211594}, {"country_id": "BE", "probability": 0.09328636822511761}]}
{"name": "pietari", "country": [{"country_id": "FI", "probability": 1}]}
{"name": "pieter", "country": [{"country_id": "NL", "probability": 0.29193759147803006}, {"country_id": "ZA", "probability": 0.28450728742112846}, {"country_id": "NA", "probability": 0.24304993743366235}]}
{"name": "pieternel", "country": []}
{"name": "pieterpaul", "country": []}
